{
  "url": "http://127.0.0.1:64092/pedidos",
  "title": "Pedidos · Via Reversa",
  "htmlClass": "",
  "bodyClass": "",
  "scroll": {
    "width": 1366,
    "height": 768
  },
  "landmarks": [
    {
      "selector": "aside",
      "tag": "aside",
      "classes": "flex min-h-0 w-full min-w-0 flex-col overflow-hidden bg-via-sidebar px-3 pt-[22px] pb-3.5 text-[oklch(90%_0.02_253)]",
      "text": "Via ReversaOperação logísticaOperaçãoHomeOperação ao vivo146PedidosLotesExpediçãoRoteirizaçãoRotasCheck InTratativasOcorrências NGDisparo ChatbotAuditoria geográficaDashboard ReversaCalendárioGestãoDa",
      "box": {
        "x": 0,
        "y": 0,
        "width": 228,
        "height": 768
      },
      "styles": {
        "display": "flex",
        "color": "oklch(0.9 0.02 253)",
        "backgroundColor": "oklch(0.25 0.04 253)",
        "fontFamily": "\"Segoe UI\", Roboto, Arial, sans-serif",
        "fontSize": "13px",
        "lineHeight": "17.94px",
        "borderRadius": "0px",
        "boxShadow": "none"
      }
    },
    {
      "selector": "header",
      "tag": "header",
      "classes": "flex h-(--app-topbar-height) items-center justify-between border-b border-via-line bg-via-surface px-5",
      "text": "HomePedidosAD",
      "box": {
        "x": 228,
        "y": 0,
        "width": 1138,
        "height": 58
      },
      "styles": {
        "display": "flex",
        "color": "oklch(0.25 0.025 253)",
        "backgroundColor": "oklch(0.99 0.004 253)",
        "fontFamily": "\"Segoe UI\", Roboto, Arial, sans-serif",
        "fontSize": "13px",
        "lineHeight": "17.94px",
        "borderRadius": "0px",
        "boxShadow": "none"
      }
    },
    {
      "selector": "main",
      "tag": "main",
      "classes": "h-[calc(100%-var(--app-topbar-height))] overflow-auto bg-via-surface bg-[#fbfdff]",
      "text": "PedidosListagem completa por recorte de status Importar ocorrências Exportar XLSX Criar pedido 28Não processadofiltrar este status18Ponto de apoio não identificadoaguardando roteirização42Back Orderag",
      "box": {
        "x": 228,
        "y": 58,
        "width": 1138,
        "height": 710
      },
      "styles": {
        "display": "block",
        "color": "oklch(0.25 0.025 253)",
        "backgroundColor": "oklch(0.99 0.004 253)",
        "fontFamily": "\"Segoe UI\", Roboto, Arial, sans-serif",
        "fontSize": "13px",
        "lineHeight": "17.94px",
        "borderRadius": "0px",
        "boxShadow": "none"
      }
    },
    {
      "selector": "nav",
      "tag": "nav",
      "classes": "min-h-0 overflow-auto [scrollbar-width:none]",
      "text": "OperaçãoHomeOperação ao vivo146PedidosLotesExpediçãoRoteirizaçãoRotasCheck InTratativasOcorrências NGDisparo ChatbotAuditoria geográficaDashboard ReversaCalendárioGestãoDashboardsSLAResumosFaturasDevo",
      "box": {
        "x": 12,
        "y": 77.109375,
        "width": 204,
        "height": 624.890625
      },
      "styles": {
        "display": "block",
        "color": "oklch(0.9 0.02 253)",
        "backgroundColor": "rgba(0, 0, 0, 0)",
        "fontFamily": "\"Segoe UI\", Roboto, Arial, sans-serif",
        "fontSize": "13px",
        "lineHeight": "17.94px",
        "borderRadius": "0px",
        "boxShadow": "none"
      }
    },
    {
      "selector": "table",
      "tag": "table",
      "classes": "min-w-[980px] w-full table-fixed border-collapse",
      "text": "PedidoStatusClienteOperaçãoPonto de apoio / transportadorUFCriadoSLAAbrir#48219Back OrderRennerTrocaNão atribuídoRJ15/07 19:02Em riscoAbrir#48208AtribuídoAmazon BRReversaPonto de apoio CentroSP15/07 1",
      "box": {
        "x": 228,
        "y": 343.96875,
        "width": 1138,
        "height": 328.5
      },
      "styles": {
        "display": "table",
        "color": "oklch(0.25 0.025 253)",
        "backgroundColor": "rgba(0, 0, 0, 0)",
        "fontFamily": "\"Segoe UI\", Roboto, Arial, sans-serif",
        "fontSize": "13px",
        "lineHeight": "17.94px",
        "borderRadius": "0px",
        "boxShadow": "none"
      }
    }
  ],
  "variables": {
    "--via-ink": "oklch(25% 0.025 253)",
    "--via-blue-strong": "oklch(53% 0.2 254)",
    "--via-blue-soft": "oklch(95% 0.035 254)",
    "--via-blue": "oklch(62% 0.19 254)",
    "--via-cyan": "oklch(69% 0.13 219)",
    "--via-sidebar": "oklch(25% 0.04 253)",
    "--via-violet": "oklch(58% 0.14 292)",
    "--via-line-strong": "oklch(82% 0.018 253)",
    "--via-surface-2": "oklch(97.5% 0.008 253)",
    "--via-muted": "oklch(51% 0.022 253)",
    "--via-line": "oklch(88% 0.012 253)",
    "--via-page": "oklch(91.5% 0.014 253)",
    "--via-amber": "oklch(68% 0.14 73)",
    "--via-red": "oklch(59% 0.19 27)",
    "--via-sidebar-line": "oklch(34% 0.04 253)",
    "--via-green": "oklch(59% 0.13 146)",
    "--via-surface-3": "oklch(94.5% 0.014 253)",
    "--via-surface": "oklch(99% 0.004 253)",
    "--via-subtle": "oklch(66% 0.018 253)"
  },
  "links": [
    {
      "text": "Home",
      "href": "/"
    },
    {
      "text": "Operação ao vivo146",
      "href": "/operacao/ao-vivo"
    },
    {
      "text": "Pedidos",
      "href": "/pedidos"
    },
    {
      "text": "Lotes",
      "href": "/operacao/lotes"
    },
    {
      "text": "Expedição",
      "href": "/operacao/expedicao"
    },
    {
      "text": "Roteirização",
      "href": "/operacao/roteirizacao"
    },
    {
      "text": "Rotas",
      "href": "/operacao/rotas"
    },
    {
      "text": "Check In",
      "href": "/loja/check-in"
    },
    {
      "text": "Tratativas",
      "href": "/operacao/tratativas"
    },
    {
      "text": "Ocorrências NG",
      "href": "/operacao/ocorrencias-ng"
    },
    {
      "text": "Disparo Chatbot",
      "href": "/operacao/disparo-chatbot"
    },
    {
      "text": "Auditoria geográfica",
      "href": "/operacao/geo-audit"
    },
    {
      "text": "Dashboard Reversa",
      "href": "/operacao/dashboard-reversa"
    },
    {
      "text": "Calendário",
      "href": "/calendario"
    },
    {
      "text": "Pontos de apoio",
      "href": "/pontos-de-apoio"
    },
    {
      "text": "Transportadores",
      "href": "/transportadores"
    },
    {
      "text": "Home",
      "href": "/"
    },
    {
      "text": "Criar pedido",
      "href": "/pedidos/novo"
    }
  ],
  "buttons": [
    {
      "text": "Dashboards",
      "disabled": false,
      "aria": null
    },
    {
      "text": "SLA",
      "disabled": false,
      "aria": null
    },
    {
      "text": "Resumos",
      "disabled": false,
      "aria": null
    },
    {
      "text": "Faturas",
      "disabled": false,
      "aria": null
    },
    {
      "text": "Devoluções",
      "disabled": false,
      "aria": null
    },
    {
      "text": "Cadastros",
      "disabled": false,
      "aria": null
    },
    {
      "text": "Configurações",
      "disabled": false,
      "aria": null
    },
    {
      "text": "Central de ajuda",
      "disabled": false,
      "aria": null
    },
    {
      "text": "",
      "disabled": false,
      "aria": "Notificações"
    },
    {
      "text": "Importar ocorrências",
      "disabled": false,
      "aria": null
    },
    {
      "text": "Exportar XLSX",
      "disabled": false,
      "aria": null
    },
    {
      "text": "Em aberto · 5",
      "disabled": false,
      "aria": null
    },
    {
      "text": "Em rota · 1",
      "disabled": false,
      "aria": null
    },
    {
      "text": "Concluídos / Ocorrências · 4",
      "disabled": false,
      "aria": null
    },
    {
      "text": "Operação",
      "disabled": false,
      "aria": null
    },
    {
      "text": "Período",
      "disabled": false,
      "aria": null
    },
    {
      "text": "Mais filtros · 3",
      "disabled": false,
      "aria": null
    },
    {
      "text": "Configurar colunas",
      "disabled": false,
      "aria": null
    },
    {
      "text": "",
      "disabled": false,
      "aria": "Selecionar todos"
    },
    {
      "text": "",
      "disabled": false,
      "aria": "Selecionar pedido 48219"
    },
    {
      "text": "",
      "disabled": false,
      "aria": "Selecionar pedido 48208"
    },
    {
      "text": "",
      "disabled": false,
      "aria": "Selecionar pedido 48201"
    },
    {
      "text": "",
      "disabled": false,
      "aria": "Selecionar pedido 48197"
    },
    {
      "text": "",
      "disabled": false,
      "aria": "Selecionar pedido 48190"
    }
  ],
  "components": [
    "bg-via-page",
    "border-0",
    "bg-via-surface",
    "bg-via-sidebar",
    "border-0",
    "border-0",
    "border-0",
    "border-0",
    "border-0",
    "border-0",
    "border-0",
    "border-0",
    "border-0",
    "border-0",
    "border-0",
    "border-0",
    "border-0",
    "i-lucide:chart-column-increasing",
    "border-0",
    "border-0",
    "border-0",
    "border-0",
    "i-lucide:chart-no-axes-combined",
    "border-0",
    "border-0",
    "border-0",
    "border-0",
    "border-0",
    "border-0",
    "border-t",
    "border-via-sidebar-line",
    "border-0",
    "bg-via-surface",
    "h-(--app-topbar-height)",
    "border-b",
    "border-via-line",
    "bg-via-surface",
    "text-via-muted",
    "hover:text-via-blue-strong",
    "hover:decoration-[color-mix(in_srgb,var(--via-blue-strong)_45%,transparent)]",
    "text-via-muted",
    "text-via-ink",
    "[&_input]:border-via-line-strong",
    "[&_input]:bg-via-surface-2",
    "border-0",
    "bg-via-blue-soft",
    "text-via-blue-strong",
    "h-[calc(100%-var(--app-topbar-height))]",
    "bg-via-surface",
    "border-b",
    "border-via-line",
    "bg-via-surface",
    "px-app-gutter",
    "[&_.app-button]:min-h-[30px]",
    "[&_.app-button]:px-2",
    "via-page-title",
    "text-via-muted",
    "app-button",
    "rounded-via-control",
    "transition-[background-color,border-color,color,transform]",
    "app-button--secondary",
    "app-button",
    "rounded-via-control",
    "transition-[background-color,border-color,color,transform]",
    "app-button--secondary",
    "app-button",
    "rounded-via-control",
    "transition-[background-color,border-color,color,transform]",
    "app-button--primary",
    "text-via-surface",
    "metrics-strip",
    "border-b",
    "border-via-line",
    "bg-via-surface",
    "border-r",
    "border-via-line",
    "text-via-subtle",
    "text-via-ink",
    "text-via-muted",
    "border-r",
    "border-via-line",
    "text-via-subtle",
    "text-via-ink",
    "text-via-muted",
    "border-r",
    "border-via-line",
    "text-via-subtle",
    "text-via-ink",
    "text-via-muted",
    "border-r-0",
    "border-r",
    "border-via-line",
    "text-via-subtle",
    "text-via-red",
    "text-via-ink",
    "text-via-muted",
    "border-b",
    "border-via-line",
    "border-via-blue",
    "text-via-ink",
    "border-0",
    "border-b-2",
    "border-transparent",
    "text-via-muted",
    "transition-[color,border-color]",
    "border-0",
    "border-b-2",
    "border-transparent",
    "text-via-muted",
    "transition-[color,border-color]",
    "border-0",
    "border-b-2",
    "border-transparent",
    "text-via-muted",
    "transition-[color,border-color]",
    "border-b",
    "border-via-line",
    "[&_input]:border-via-line-strong",
    "[&_input]:bg-via-surface-2",
    "border-0",
    "app-button",
    "rounded-via-control",
    "transition-[background-color,border-color,color,transform]",
    "app-button--secondary",
    "app-button",
    "rounded-via-control",
    "transition-[background-color,border-color,color,transform]",
    "app-button--secondary",
    "app-button",
    "rounded-via-control",
    "transition-[background-color,border-color,color,transform]",
    "app-button--secondary",
    "table-fixed",
    "border-collapse",
    "border-b",
    "border-via-line",
    "bg-via-surface-2",
    "text-via-muted",
    "border",
    "border-via-line-strong",
    "bg-via-surface",
    "border-b",
    "border-via-line",
    "bg-via-surface-2",
    "text-via-muted",
    "border-b",
    "border-via-line",
    "bg-via-surface-2",
    "text-via-muted",
    "border-b",
    "border-via-line",
    "bg-via-surface-2",
    "text-via-muted",
    "border-b",
    "border-via-line",
    "bg-via-surface-2",
    "text-via-muted",
    "border-b",
    "border-via-line",
    "bg-via-surface-2",
    "text-via-muted",
    "border-b",
    "border-via-line",
    "bg-via-surface-2",
    "text-via-muted",
    "border-b",
    "border-via-line",
    "bg-via-surface-2",
    "text-via-muted",
    "border-b",
    "border-via-line",
    "bg-via-surface-2",
    "text-via-muted",
    "border-b",
    "border-via-line",
    "bg-via-surface-2",
    "text-via-muted",
    "hover:bg-via-blue-soft",
    "hover:shadow-[inset_3px_0_0_var(--via-blue)]",
    "focus-visible:bg-via-blue-soft",
    "focus-visible:shadow-[inset_3px_0_0_var(--via-blue)]",
    "border-b",
    "border-via-line",
    "text-via-ink",
    "border",
    "border-via-line-strong",
    "bg-via-surface",
    "border-b",
    "border-via-line",
    "text-via-ink",
    "border-b",
    "border-via-line",
    "text-via-ink",
    "text-via-ink",
    "border-b",
    "border-via-line",
    "text-via-ink",
    "border-b",
    "border-via-line",
    "text-via-ink"
  ],
  "requestLog": [
    {
      "url": "http://127.0.0.1:64092/_nuxt/@fs/D:/DEVJUANMARCOS/PROJETOS/KEENER/VIA%20REVERSA/V2/ViaReversaV2_Front/node_modules/reka-ui/dist/MonthPicker/MonthPickerPrev.js?v=c692b6b6",
      "method": "GET",
      "failure": "net::ERR_ABORTED"
    },
    {
      "url": "http://127.0.0.1:64092/_nuxt/@fs/D:/DEVJUANMARCOS/PROJETOS/KEENER/VIA%20REVERSA/V2/ViaReversaV2_Front/node_modules/reka-ui/dist/Toolbar/ToolbarRoot.js?v=c692b6b6",
      "method": "GET",
      "failure": "net::ERR_ABORTED"
    },
    {
      "url": "http://127.0.0.1:64092/_nuxt/@fs/D:/DEVJUANMARCOS/PROJETOS/KEENER/VIA%20REVERSA/V2/ViaReversaV2_Front/node_modules/reka-ui/dist/Tree/TreeRoot.js?v=c692b6b6",
      "method": "GET",
      "failure": "net::ERR_ABORTED"
    },
    {
      "url": "http://127.0.0.1:64092/_nuxt/@fs/D:/DEVJUANMARCOS/PROJETOS/KEENER/VIA%20REVERSA/V2/ViaReversaV2_Front/node_modules/reka-ui/dist/YearRangePicker/YearRangePickerGridRow.js?v=c692b6b6",
      "method": "GET",
      "failure": "net::ERR_ABORTED"
    },
    {
      "url": "http://127.0.0.1:64092/_nuxt/@fs/D:/DEVJUANMARCOS/PROJETOS/KEENER/VIA%20REVERSA/V2/ViaReversaV2_Front/node_modules/reka-ui/dist/YearPicker/YearPickerCell.js?v=c692b6b6",
      "method": "GET",
      "failure": "net::ERR_ABORTED"
    },
    {
      "url": "http://127.0.0.1:64092/_nuxt/@fs/D:/DEVJUANMARCOS/PROJETOS/KEENER/VIA%20REVERSA/V2/ViaReversaV2_Front/node_modules/reka-ui/dist/ScrollArea/ScrollAreaScrollbarImpl.js?v=c692b6b6",
      "method": "GET",
      "failure": "net::ERR_ABORTED"
    },
    {
      "url": "http://127.0.0.1:64092/_nuxt/@fs/D:/DEVJUANMARCOS/PROJETOS/KEENER/VIA%20REVERSA/V2/ViaReversaV2_Front/node_modules/reka-ui/dist/MonthRangePicker/MonthRangePickerRoot.js?v=c692b6b6",
      "method": "GET",
      "failure": "net::ERR_ABORTED"
    },
    {
      "url": "http://127.0.0.1:64092/_nuxt/@fs/D:/DEVJUANMARCOS/PROJETOS/KEENER/VIA%20REVERSA/V2/ViaReversaV2_Front/node_modules/reka-ui/dist/ToggleGroup/ToggleGroupRoot.js?v=c692b6b6",
      "method": "GET",
      "failure": "net::ERR_ABORTED"
    },
    {
      "url": "http://127.0.0.1:64092/_nuxt/@fs/D:/DEVJUANMARCOS/PROJETOS/KEENER/VIA%20REVERSA/V2/ViaReversaV2_Front/node_modules/reka-ui/dist/Toast/ToastRootImpl.js?v=c692b6b6",
      "method": "GET",
      "failure": "net::ERR_ABORTED"
    },
    {
      "url": "http://127.0.0.1:64092/_nuxt/@fs/D:/DEVJUANMARCOS/PROJETOS/KEENER/VIA%20REVERSA/V2/ViaReversaV2_Front/node_modules/reka-ui/dist/NavigationMenu/NavigationMenuRoot.js?v=c692b6b6",
      "method": "GET",
      "failure": "net::ERR_ABORTED"
    },
    {
      "url": "http://127.0.0.1:64092/_nuxt/@fs/D:/DEVJUANMARCOS/PROJETOS/KEENER/VIA%20REVERSA/V2/ViaReversaV2_Front/node_modules/reka-ui/dist/Select/SelectRoot.js?v=c692b6b6",
      "method": "GET",
      "failure": "net::ERR_ABORTED"
    },
    {
      "url": "http://127.0.0.1:64092/_nuxt/@fs/D:/DEVJUANMARCOS/PROJETOS/KEENER/VIA%20REVERSA/V2/ViaReversaV2_Front/node_modules/@nuxt/ui/dist/runtime/composables/useComponentProps.js?v=c692b6b6",
      "method": "GET",
      "failure": "net::ERR_ABORTED"
    },
    {
      "url": "http://127.0.0.1:64092/_nuxt/@fs/D:/DEVJUANMARCOS/PROJETOS/KEENER/VIA%20REVERSA/V2/ViaReversaV2_Front/node_modules/reka-ui/dist/NumberField/NumberFieldIncrement.js?v=c692b6b6",
      "method": "GET",
      "failure": "net::ERR_ABORTED"
    },
    {
      "url": "http://127.0.0.1:64092/_nuxt/@fs/D:/DEVJUANMARCOS/PROJETOS/KEENER/VIA%20REVERSA/V2/ViaReversaV2_Front/node_modules/reka-ui/dist/NumberField/NumberFieldRoot.js?v=c692b6b6",
      "method": "GET",
      "failure": "net::ERR_ABORTED"
    },
    {
      "url": "http://127.0.0.1:64092/_nuxt/@fs/D:/DEVJUANMARCOS/PROJETOS/KEENER/VIA%20REVERSA/V2/ViaReversaV2_Front/node_modules/reka-ui/dist/Select/SelectItemText.js?v=c692b6b6",
      "method": "GET",
      "failure": "net::ERR_ABORTED"
    },
    {
      "url": "http://127.0.0.1:64092/_nuxt/@fs/D:/DEVJUANMARCOS/PROJETOS/KEENER/VIA%20REVERSA/V2/ViaReversaV2_Front/node_modules/reka-ui/dist/MonthRangePicker/MonthRangePickerGrid.js?v=c692b6b6",
      "method": "GET",
      "failure": "net::ERR_ABORTED"
    },
    {
      "url": "http://127.0.0.1:64092/_nuxt/@fs/D:/DEVJUANMARCOS/PROJETOS/KEENER/VIA%20REVERSA/V2/ViaReversaV2_Front/node_modules/reka-ui/dist/Tabs/TabsIndicator.js?v=c692b6b6",
      "method": "GET",
      "failure": "net::ERR_ABORTED"
    },
    {
      "url": "http://127.0.0.1:64092/_nuxt/@fs/D:/DEVJUANMARCOS/PROJETOS/KEENER/VIA%20REVERSA/V2/ViaReversaV2_Front/node_modules/reka-ui/dist/RangeCalendar/RangeCalendarPrev.js?v=c692b6b6",
      "method": "GET",
      "failure": "net::ERR_ABORTED"
    },
    {
      "url": "http://127.0.0.1:64092/_nuxt/@fs/D:/DEVJUANMARCOS/PROJETOS/KEENER/VIA%20REVERSA/V2/ViaReversaV2_Front/node_modules/reka-ui/dist/Pagination/PaginationRoot.js?v=c692b6b6",
      "method": "GET",
      "failure": "net::ERR_ABORTED"
    },
    {
      "url": "http://127.0.0.1:64092/_nuxt/@fs/D:/DEVJUANMARCOS/PROJETOS/KEENER/VIA%20REVERSA/V2/ViaReversaV2_Front/node_modules/reka-ui/dist/utils/events.js?v=c692b6b6",
      "method": "GET",
      "failure": "net::ERR_ABORTED"
    },
    {
      "url": "http://127.0.0.1:64092/_nuxt/@fs/D:/DEVJUANMARCOS/PROJETOS/KEENER/VIA%20REVERSA/V2/ViaReversaV2_Front/node_modules/reka-ui/dist/MonthRangePicker/MonthRangePickerCell.js?v=c692b6b6",
      "method": "GET",
      "failure": "net::ERR_ABORTED"
    },
    {
      "url": "http://127.0.0.1:64092/_nuxt/@fs/D:/DEVJUANMARCOS/PROJETOS/KEENER/VIA%20REVERSA/V2/ViaReversaV2_Front/node_modules/reka-ui/dist/RadioGroup/RadioGroupRoot.js?v=c692b6b6",
      "method": "GET",
      "failure": "net::ERR_ABORTED"
    },
    {
      "url": "http://127.0.0.1:64092/_nuxt/@fs/D:/DEVJUANMARCOS/PROJETOS/KEENER/VIA%20REVERSA/V2/ViaReversaV2_Front/node_modules/reka-ui/dist/TagsInput/TagsInputClear.js?v=c692b6b6",
      "method": "GET",
      "failure": "net::ERR_ABORTED"
    },
    {
      "url": "http://127.0.0.1:64092/_nuxt/@fs/D:/DEVJUANMARCOS/PROJETOS/KEENER/VIA%20REVERSA/V2/ViaReversaV2_Front/node_modules/reka-ui/dist/MonthPicker/MonthPickerGrid.js?v=c692b6b6",
      "method": "GET",
      "failure": "net::ERR_ABORTED"
    },
    {
      "url": "http://127.0.0.1:64092/_nuxt/@fs/D:/DEVJUANMARCOS/PROJETOS/KEENER/VIA%20REVERSA/V2/ViaReversaV2_Front/node_modules/reka-ui/dist/NavigationMenu/NavigationMenuItem.js?v=c692b6b6",
      "method": "GET",
      "failure": "net::ERR_ABORTED"
    },
    {
      "url": "http://127.0.0.1:64092/_nuxt/@fs/D:/DEVJUANMARCOS/PROJETOS/KEENER/VIA%20REVERSA/V2/ViaReversaV2_Front/node_modules/reka-ui/dist/Tabs/TabsRoot.js?v=c692b6b6",
      "method": "GET",
      "failure": "net::ERR_ABORTED"
    },
    {
      "url": "http://127.0.0.1:64092/_nuxt/@fs/D:/DEVJUANMARCOS/PROJETOS/KEENER/VIA%20REVERSA/V2/ViaReversaV2_Front/node_modules/reka-ui/dist/Switch/SwitchThumb.js?v=c692b6b6",
      "method": "GET",
      "failure": "net::ERR_ABORTED"
    },
    {
      "url": "http://127.0.0.1:64092/_nuxt/@fs/D:/DEVJUANMARCOS/PROJETOS/KEENER/VIA%20REVERSA/V2/ViaReversaV2_Front/node_modules/reka-ui/dist/Menubar/MenubarPortal.js?v=c692b6b6",
      "method": "GET",
      "failure": "net::ERR_ABORTED"
    },
    {
      "url": "http://127.0.0.1:64092/_nuxt/@fs/D:/DEVJUANMARCOS/PROJETOS/KEENER/VIA%20REVERSA/V2/ViaReversaV2_Front/node_modules/reka-ui/dist/Toggle/Toggle.js?v=c692b6b6",
      "method": "GET",
      "failure": "net::ERR_ABORTED"
    },
    {
      "url": "http://127.0.0.1:64092/_nuxt/@fs/D:/DEVJUANMARCOS/PROJETOS/KEENER/VIA%20REVERSA/V2/ViaReversaV2_Front/node_modules/reka-ui/dist/Toast/ToastDescription.js?v=c692b6b6",
      "method": "GET",
      "failure": "net::ERR_ABORTED"
    },
    {
      "url": "http://127.0.0.1:64092/_nuxt/@fs/D:/DEVJUANMARCOS/PROJETOS/KEENER/VIA%20REVERSA/V2/ViaReversaV2_Front/node_modules/reka-ui/dist/Editable/EditablePreview.js?v=c692b6b6",
      "method": "GET",
      "failure": "net::ERR_ABORTED"
    },
    {
      "url": "http://127.0.0.1:64092/_nuxt/@fs/D:/DEVJUANMARCOS/PROJETOS/KEENER/VIA%20REVERSA/V2/ViaReversaV2_Front/node_modules/reka-ui/dist/Menubar/MenubarMenu.js?v=c692b6b6",
      "method": "GET",
      "failure": "net::ERR_ABORTED"
    },
    {
      "url": "http://127.0.0.1:64092/_nuxt/@fs/D:/DEVJUANMARCOS/PROJETOS/KEENER/VIA%20REVERSA/V2/ViaReversaV2_Front/node_modules/reka-ui/dist/Popover/PopoverContentModal.js?v=c692b6b6",
      "method": "GET",
      "failure": "net::ERR_ABORTED"
    },
    {
      "url": "http://127.0.0.1:64092/_nuxt/@fs/D:/DEVJUANMARCOS/PROJETOS/KEENER/VIA%20REVERSA/V2/ViaReversaV2_Front/node_modules/reka-ui/dist/TagsInput/TagsInputItemDelete.js?v=c692b6b6",
      "method": "GET",
      "failure": "net::ERR_ABORTED"
    },
    {
      "url": "http://127.0.0.1:64092/_nuxt/@fs/D:/DEVJUANMARCOS/PROJETOS/KEENER/VIA%20REVERSA/V2/ViaReversaV2_Front/node_modules/reka-ui/dist/Viewport/Viewport.js?v=c692b6b6",
      "method": "GET",
      "failure": "net::ERR_ABORTED"
    },
    {
      "url": "http://127.0.0.1:64092/_nuxt/@fs/D:/DEVJUANMARCOS/PROJETOS/KEENER/VIA%20REVERSA/V2/ViaReversaV2_Front/node_modules/@internationalized/date/dist/index.mjs?v=c692b6b6",
      "method": "GET",
      "failure": "net::ERR_ABORTED"
    },
    {
      "url": "http://127.0.0.1:64092/_nuxt/@fs/D:/DEVJUANMARCOS/PROJETOS/KEENER/VIA%20REVERSA/V2/ViaReversaV2_Front/node_modules/reka-ui/dist/MonthPicker/useMonthPicker.js?v=c692b6b6",
      "method": "GET",
      "failure": "net::ERR_ABORTED"
    },
    {
      "url": "http://127.0.0.1:64092/_nuxt/@fs/D:/DEVJUANMARCOS/PROJETOS/KEENER/VIA%20REVERSA/V2/ViaReversaV2_Front/node_modules/reka-ui/dist/Pagination/PaginationList.js?v=c692b6b6",
      "method": "GET",
      "failure": "net::ERR_ABORTED"
    },
    {
      "url": "http://127.0.0.1:64092/_nuxt/@fs/D:/DEVJUANMARCOS/PROJETOS/KEENER/VIA%20REVERSA/V2/ViaReversaV2_Front/node_modules/reka-ui/dist/utils/storage.js?v=c692b6b6",
      "method": "GET",
      "failure": "net::ERR_ABORTED"
    },
    {
      "url": "http://127.0.0.1:64092/_nuxt/@fs/D:/DEVJUANMARCOS/PROJETOS/KEENER/VIA%20REVERSA/V2/ViaReversaV2_Front/node_modules/reka-ui/dist/HoverCard/HoverCardRoot.js?v=c692b6b6",
      "method": "GET",
      "failure": "net::ERR_ABORTED"
    },
    {
      "url": "http://127.0.0.1:64092/_nuxt/@fs/D:/DEVJUANMARCOS/PROJETOS/KEENER/VIA%20REVERSA/V2/ViaReversaV2_Front/node_modules/reka-ui/dist/Menubar/MenubarItem.js?v=c692b6b6",
      "method": "GET",
      "failure": "net::ERR_ABORTED"
    },
    {
      "url": "http://127.0.0.1:64092/_nuxt/@fs/D:/DEVJUANMARCOS/PROJETOS/KEENER/VIA%20REVERSA/V2/ViaReversaV2_Front/node_modules/reka-ui/dist/Toast/ToastAnnounce.js?v=c692b6b6",
      "method": "GET",
      "failure": "net::ERR_ABORTED"
    },
    {
      "url": "http://127.0.0.1:64092/_nuxt/@fs/D:/DEVJUANMARCOS/PROJETOS/KEENER/VIA%20REVERSA/V2/ViaReversaV2_Front/node_modules/@vueuse/shared/dist/index.js?v=c692b6b6",
      "method": "GET",
      "failure": "net::ERR_ABORTED"
    },
    {
      "url": "http://127.0.0.1:64092/_nuxt/@fs/D:/DEVJUANMARCOS/PROJETOS/KEENER/VIA%20REVERSA/V2/ViaReversaV2_Front/node_modules/reka-ui/dist/utils/registry.js?v=c692b6b6",
      "method": "GET",
      "failure": "net::ERR_ABORTED"
    },
    {
      "url": "http://127.0.0.1:64092/_nuxt/@fs/D:/DEVJUANMARCOS/PROJETOS/KEENER/VIA%20REVERSA/V2/ViaReversaV2_Front/node_modules/reka-ui/dist/Toolbar/ToolbarSeparator.js?v=c692b6b6",
      "method": "GET",
      "failure": "net::ERR_ABORTED"
    },
    {
      "url": "http://127.0.0.1:64092/_nuxt/@fs/D:/DEVJUANMARCOS/PROJETOS/KEENER/VIA%20REVERSA/V2/ViaReversaV2_Front/node_modules/reka-ui/dist/Select/SelectPopperPosition.js?v=c692b6b6",
      "method": "GET",
      "failure": "net::ERR_ABORTED"
    },
    {
      "url": "http://127.0.0.1:64092/_nuxt/@fs/D:/DEVJUANMARCOS/PROJETOS/KEENER/VIA%20REVERSA/V2/ViaReversaV2_Front/node_modules/reka-ui/dist/composables/useWindowSplitterBehavior.js?v=c692b6b6",
      "method": "GET",
      "failure": "net::ERR_ABORTED"
    },
    {
      "url": "http://127.0.0.1:64092/_nuxt/@fs/D:/DEVJUANMARCOS/PROJETOS/KEENER/VIA%20REVERSA/V2/ViaReversaV2_Front/node_modules/reka-ui/dist/RangeCalendar/RangeCalendarGridRow.js?v=c692b6b6",
      "method": "GET",
      "failure": "net::ERR_ABORTED"
    },
    {
      "url": "http://127.0.0.1:64092/_nuxt/@fs/D:/DEVJUANMARCOS/PROJETOS/KEENER/VIA%20REVERSA/V2/ViaReversaV2_Front/node_modules/reka-ui/dist/RangeCalendar/RangeCalendarCell.js?v=c692b6b6",
      "method": "GET",
      "failure": "net::ERR_ABORTED"
    },
    {
      "url": "http://127.0.0.1:64092/_nuxt/@fs/D:/DEVJUANMARCOS/PROJETOS/KEENER/VIA%20REVERSA/V2/ViaReversaV2_Front/node_modules/reka-ui/dist/Tooltip/TooltipContentHoverable.js?v=c692b6b6",
      "method": "GET",
      "failure": "net::ERR_ABORTED"
    },
    {
      "url": "http://127.0.0.1:64092/_nuxt/@fs/D:/DEVJUANMARCOS/PROJETOS/KEENER/VIA%20REVERSA/V2/ViaReversaV2_Front/node_modules/reka-ui/dist/Separator/Separator.js?v=c692b6b6",
      "method": "GET",
      "failure": "net::ERR_ABORTED"
    },
    {
      "url": "http://127.0.0.1:64092/_nuxt/@fs/D:/DEVJUANMARCOS/PROJETOS/KEENER/VIA%20REVERSA/V2/ViaReversaV2_Front/node_modules/reka-ui/dist/Select/SelectPortal.js?v=c692b6b6",
      "method": "GET",
      "failure": "net::ERR_ABORTED"
    },
    {
      "url": "http://127.0.0.1:64092/_nuxt/@fs/D:/DEVJUANMARCOS/PROJETOS/KEENER/VIA%20REVERSA/V2/ViaReversaV2_Front/node_modules/reka-ui/dist/Popover/PopoverContentNonModal.js?v=c692b6b6",
      "method": "GET",
      "failure": "net::ERR_ABORTED"
    },
    {
      "url": "http://127.0.0.1:64092/_nuxt/@fs/D:/DEVJUANMARCOS/PROJETOS/KEENER/VIA%20REVERSA/V2/ViaReversaV2_Front/node_modules/reka-ui/dist/Menubar/MenubarRadioItem.js?v=c692b6b6",
      "method": "GET",
      "failure": "net::ERR_ABORTED"
    },
    {
      "url": "http://127.0.0.1:64092/_nuxt/@fs/D:/DEVJUANMARCOS/PROJETOS/KEENER/VIA%20REVERSA/V2/ViaReversaV2_Front/node_modules/reka-ui/dist/Toolbar/ToolbarToggleItem.js?v=c692b6b6",
      "method": "GET",
      "failure": "net::ERR_ABORTED"
    },
    {
      "url": "http://127.0.0.1:64092/_nuxt/@fs/D:/DEVJUANMARCOS/PROJETOS/KEENER/VIA%20REVERSA/V2/ViaReversaV2_Front/node_modules/reka-ui/dist/Popover/PopoverRoot.js?v=c692b6b6",
      "method": "GET",
      "failure": "net::ERR_ABORTED"
    },
    {
      "url": "http://127.0.0.1:64092/_nuxt/@fs/D:/DEVJUANMARCOS/PROJETOS/KEENER/VIA%20REVERSA/V2/ViaReversaV2_Front/node_modules/reka-ui/dist/Tooltip/TooltipContentImpl.js?v=c692b6b6",
      "method": "GET",
      "failure": "net::ERR_ABORTED"
    },
    {
      "url": "http://127.0.0.1:64092/_nuxt/@fs/D:/DEVJUANMARCOS/PROJETOS/KEENER/VIA%20REVERSA/V2/ViaReversaV2_Front/node_modules/reka-ui/dist/MonthRangePicker/MonthRangePickerPrev.js?v=c692b6b6",
      "method": "GET",
      "failure": "net::ERR_ABORTED"
    },
    {
      "url": "http://127.0.0.1:64092/_nuxt/@fs/D:/DEVJUANMARCOS/PROJETOS/KEENER/VIA%20REVERSA/V2/ViaReversaV2_Front/node_modules/reka-ui/dist/YearRangePicker/YearRangePickerCell.js?v=c692b6b6",
      "method": "GET",
      "failure": "net::ERR_ABORTED"
    },
    {
      "url": "http://127.0.0.1:64092/_nuxt/@fs/D:/DEVJUANMARCOS/PROJETOS/KEENER/VIA%20REVERSA/V2/ViaReversaV2_Front/node_modules/reka-ui/dist/Select/SelectGroup.js?v=c692b6b6",
      "method": "GET",
      "failure": "net::ERR_ABORTED"
    },
    {
      "url": "http://127.0.0.1:64092/_nuxt/@fs/D:/DEVJUANMARCOS/PROJETOS/KEENER/VIA%20REVERSA/V2/ViaReversaV2_Front/node_modules/reka-ui/dist/TimeRangeField/TimeRangeFieldInput.js?v=c692b6b6",
      "method": "GET",
      "failure": "net::ERR_ABORTED"
    },
    {
      "url": "http://127.0.0.1:64092/_nuxt/@fs/D:/DEVJUANMARCOS/PROJETOS/KEENER/VIA%20REVERSA/V2/ViaReversaV2_Front/node_modules/reka-ui/dist/TimeRangeField/TimeRangeFieldRoot.js?v=c692b6b6",
      "method": "GET",
      "failure": "net::ERR_ABORTED"
    },
    {
      "url": "http://127.0.0.1:64092/_nuxt/@fs/D:/DEVJUANMARCOS/PROJETOS/KEENER/VIA%20REVERSA/V2/ViaReversaV2_Front/node_modules/reka-ui/dist/ScrollArea/ScrollAreaScrollbarHover.js?v=c692b6b6",
      "method": "GET",
      "failure": "net::ERR_ABORTED"
    },
    {
      "url": "http://127.0.0.1:64092/_nuxt/@fs/D:/DEVJUANMARCOS/PROJETOS/KEENER/VIA%20REVERSA/V2/ViaReversaV2_Front/node_modules/reka-ui/dist/Toolbar/ToolbarButton.js?v=c692b6b6",
      "method": "GET",
      "failure": "net::ERR_ABORTED"
    },
    {
      "url": "http://127.0.0.1:64092/_nuxt/@fs/D:/DEVJUANMARCOS/PROJETOS/KEENER/VIA%20REVERSA/V2/ViaReversaV2_Front/node_modules/reka-ui/dist/Editable/EditableInput.js?v=c692b6b6",
      "method": "GET",
      "failure": "net::ERR_ABORTED"
    },
    {
      "url": "http://127.0.0.1:64092/_nuxt/@fs/D:/DEVJUANMARCOS/PROJETOS/KEENER/VIA%20REVERSA/V2/ViaReversaV2_Front/node_modules/reka-ui/dist/RangeCalendar/useRangeCalendar.js?v=c692b6b6",
      "method": "GET",
      "failure": "net::ERR_ABORTED"
    },
    {
      "url": "http://127.0.0.1:64092/_nuxt/@fs/D:/DEVJUANMARCOS/PROJETOS/KEENER/VIA%20REVERSA/V2/ViaReversaV2_Front/node_modules/reka-ui/dist/PinInput/PinInputRoot.js?v=c692b6b6",
      "method": "GET",
      "failure": "net::ERR_ABORTED"
    },
    {
      "url": "http://127.0.0.1:64092/_nuxt/@fs/D:/DEVJUANMARCOS/PROJETOS/KEENER/VIA%20REVERSA/V2/ViaReversaV2_Front/node_modules/reka-ui/dist/Toast/ToastViewport.js?v=c692b6b6",
      "method": "GET",
      "failure": "net::ERR_ABORTED"
    },
    {
      "url": "http://127.0.0.1:64092/_nuxt/@fs/D:/DEVJUANMARCOS/PROJETOS/KEENER/VIA%20REVERSA/V2/ViaReversaV2_Front/node_modules/reka-ui/dist/YearPicker/useYearPicker.js?v=c692b6b6",
      "method": "GET",
      "failure": "net::ERR_ABORTED"
    },
    {
      "url": "http://127.0.0.1:64092/_nuxt/@fs/D:/DEVJUANMARCOS/PROJETOS/KEENER/VIA%20REVERSA/V2/ViaReversaV2_Front/node_modules/reka-ui/dist/Pagination/utils.js?v=c692b6b6",
      "method": "GET",
      "failure": "net::ERR_ABORTED"
    },
    {
      "url": "http://127.0.0.1:64092/_nuxt/@fs/D:/DEVJUANMARCOS/PROJETOS/KEENER/VIA%20REVERSA/V2/ViaReversaV2_Front/node_modules/@nuxt/ui/dist/runtime/composables/useForwardProps.js?v=c692b6b6",
      "method": "GET",
      "failure": "net::ERR_ABORTED"
    },
    {
      "url": "http://127.0.0.1:64092/_nuxt/@fs/D:/DEVJUANMARCOS/PROJETOS/KEENER/VIA%20REVERSA/V2/ViaReversaV2_Front/node_modules/reka-ui/dist/Editable/EditableEditTrigger.js?v=c692b6b6",
      "method": "GET",
      "failure": "net::ERR_ABORTED"
    },
    {
      "url": "http://127.0.0.1:64092/_nuxt/@fs/D:/DEVJUANMARCOS/PROJETOS/KEENER/VIA%20REVERSA/V2/ViaReversaV2_Front/node_modules/reka-ui/dist/Select/SelectItemAlignedPosition.js?v=c692b6b6",
      "method": "GET",
      "failure": "net::ERR_ABORTED"
    },
    {
      "url": "http://127.0.0.1:64092/_nuxt/@fs/D:/DEVJUANMARCOS/PROJETOS/KEENER/VIA%20REVERSA/V2/ViaReversaV2_Front/node_modules/reka-ui/dist/Tooltip/TooltipArrow.js?v=c692b6b6",
      "method": "GET",
      "failure": "net::ERR_ABORTED"
    },
    {
      "url": "http://127.0.0.1:64092/_nuxt/@fs/D:/DEVJUANMARCOS/PROJETOS/KEENER/VIA%20REVERSA/V2/ViaReversaV2_Front/node_modules/reka-ui/dist/Menubar/MenubarSeparator.js?v=c692b6b6",
      "method": "GET",
      "failure": "net::ERR_ABORTED"
    },
    {
      "url": "http://127.0.0.1:64092/_nuxt/@fs/D:/DEVJUANMARCOS/PROJETOS/KEENER/VIA%20REVERSA/V2/ViaReversaV2_Front/node_modules/reka-ui/dist/Menubar/MenubarContent.js?v=c692b6b6",
      "method": "GET",
      "failure": "net::ERR_ABORTED"
    },
    {
      "url": "http://127.0.0.1:64092/_nuxt/@fs/D:/DEVJUANMARCOS/PROJETOS/KEENER/VIA%20REVERSA/V2/ViaReversaV2_Front/node_modules/reka-ui/dist/Toast/ToastProvider.js?v=c692b6b6",
      "method": "GET",
      "failure": "net::ERR_ABORTED"
    },
    {
      "url": "http://127.0.0.1:64092/_nuxt/@fs/D:/DEVJUANMARCOS/PROJETOS/KEENER/VIA%20REVERSA/V2/ViaReversaV2_Front/node_modules/reka-ui/dist/YearRangePicker/YearRangePickerCellTrigger.js?v=c692b6b6",
      "method": "GET",
      "failure": "net::ERR_ABORTED"
    },
    {
      "url": "http://127.0.0.1:64092/_nuxt/@fs/D:/DEVJUANMARCOS/PROJETOS/KEENER/VIA%20REVERSA/V2/ViaReversaV2_Front/node_modules/reka-ui/dist/utils/pivot.js?v=c692b6b6",
      "method": "GET",
      "failure": "net::ERR_ABORTED"
    },
    {
      "url": "http://127.0.0.1:64092/_nuxt/@fs/D:/DEVJUANMARCOS/PROJETOS/KEENER/VIA%20REVERSA/V2/ViaReversaV2_Front/node_modules/reka-ui/dist/RangeCalendar/RangeCalendarGrid.js?v=c692b6b6",
      "method": "GET",
      "failure": "net::ERR_ABORTED"
    },
    {
      "url": "http://127.0.0.1:64092/_nuxt/@fs/D:/DEVJUANMARCOS/PROJETOS/KEENER/VIA%20REVERSA/V2/ViaReversaV2_Front/node_modules/reka-ui/dist/utils/rects.js?v=c692b6b6",
      "method": "GET",
      "failure": "net::ERR_ABORTED"
    },
    {
      "url": "http://127.0.0.1:64092/_nuxt/@fs/D:/DEVJUANMARCOS/PROJETOS/KEENER/VIA%20REVERSA/V2/ViaReversaV2_Front/node_modules/reka-ui/dist/Select/utils.js?v=c692b6b6",
      "method": "GET",
      "failure": "net::ERR_ABORTED"
    },
    {
      "url": "http://127.0.0.1:64092/_nuxt/@fs/D:/DEVJUANMARCOS/PROJETOS/KEENER/VIA%20REVERSA/V2/ViaReversaV2_Front/node_modules/@floating-ui/vue/dist/floating-ui.vue.mjs?v=c692b6b6",
      "method": "GET",
      "failure": "net::ERR_ABORTED"
    },
    {
      "url": "http://127.0.0.1:64092/_nuxt/@fs/D:/DEVJUANMARCOS/PROJETOS/KEENER/VIA%20REVERSA/V2/ViaReversaV2_Front/node_modules/@nuxt/ui/dist/runtime/utils/index.js?v=c692b6b6",
      "method": "GET",
      "failure": "net::ERR_ABORTED"
    },
    {
      "url": "http://127.0.0.1:64092/_nuxt/@fs/D:/DEVJUANMARCOS/PROJETOS/KEENER/VIA%20REVERSA/V2/ViaReversaV2_Front/node_modules/reka-ui/dist/MonthRangePicker/MonthRangePickerGridBody.js?v=c692b6b6",
      "method": "GET",
      "failure": "net::ERR_ABORTED"
    },
    {
      "url": "http://127.0.0.1:64092/_nuxt/@fs/D:/DEVJUANMARCOS/PROJETOS/KEENER/VIA%20REVERSA/V2/ViaReversaV2_Front/node_modules/reka-ui/dist/Tooltip/utils.js?v=c692b6b6",
      "method": "GET",
      "failure": "net::ERR_ABORTED"
    },
    {
      "url": "http://127.0.0.1:64092/_nuxt/@fs/D:/DEVJUANMARCOS/PROJETOS/KEENER/VIA%20REVERSA/V2/ViaReversaV2_Front/node_modules/reka-ui/dist/Label/Label.js?v=c692b6b6",
      "method": "GET",
      "failure": "net::ERR_ABORTED"
    },
    {
      "url": "http://127.0.0.1:64092/_nuxt/@fs/D:/DEVJUANMARCOS/PROJETOS/KEENER/VIA%20REVERSA/V2/ViaReversaV2_Front/node_modules/reka-ui/dist/YearRangePicker/YearRangePickerHeader.js?v=c692b6b6",
      "method": "GET",
      "failure": "net::ERR_ABORTED"
    },
    {
      "url": "http://127.0.0.1:64092/_nuxt/@fs/D:/DEVJUANMARCOS/PROJETOS/KEENER/VIA%20REVERSA/V2/ViaReversaV2_Front/node_modules/reka-ui/dist/MonthRangePicker/MonthRangePickerNext.js?v=c692b6b6",
      "method": "GET",
      "failure": "net::ERR_ABORTED"
    },
    {
      "url": "http://127.0.0.1:64092/_nuxt/@fs/D:/DEVJUANMARCOS/PROJETOS/KEENER/VIA%20REVERSA/V2/ViaReversaV2_Front/node_modules/reka-ui/dist/YearRangePicker/YearRangePickerRoot.js?v=c692b6b6",
      "method": "GET",
      "failure": "net::ERR_ABORTED"
    },
    {
      "url": "http://127.0.0.1:64092/_nuxt/@fs/D:/DEVJUANMARCOS/PROJETOS/KEENER/VIA%20REVERSA/V2/ViaReversaV2_Front/node_modules/reka-ui/dist/YearRangePicker/useRangeYearPicker.js?v=c692b6b6",
      "method": "GET",
      "failure": "net::ERR_ABORTED"
    },
    {
      "url": "http://127.0.0.1:64092/_nuxt/@fs/D:/DEVJUANMARCOS/PROJETOS/KEENER/VIA%20REVERSA/V2/ViaReversaV2_Front/node_modules/reka-ui/dist/Stepper/StepperRoot.js?v=c692b6b6",
      "method": "GET",
      "failure": "net::ERR_ABORTED"
    },
    {
      "url": "http://127.0.0.1:64092/_nuxt/@fs/D:/DEVJUANMARCOS/PROJETOS/KEENER/VIA%20REVERSA/V2/ViaReversaV2_Front/node_modules/reka-ui/dist/Progress/ProgressRoot.js?v=c692b6b6",
      "method": "GET",
      "failure": "net::ERR_ABORTED"
    },
    {
      "url": "http://127.0.0.1:64092/_nuxt/@fs/D:/DEVJUANMARCOS/PROJETOS/KEENER/VIA%20REVERSA/V2/ViaReversaV2_Front/node_modules/@nuxt/ui/dist/runtime/composables/useToast.js?v=c692b6b6",
      "method": "GET",
      "failure": "net::ERR_ABORTED"
    },
    {
      "url": "http://127.0.0.1:64092/_nuxt/@fs/D:/DEVJUANMARCOS/PROJETOS/KEENER/VIA%20REVERSA/V2/ViaReversaV2_Front/node_modules/reka-ui/dist/ScrollArea/ScrollAreaScrollbarVisible.js?v=c692b6b6",
      "method": "GET",
      "failure": "net::ERR_ABORTED"
    },
    {
      "url": "http://127.0.0.1:64092/_nuxt/@fs/D:/DEVJUANMARCOS/PROJETOS/KEENER/VIA%20REVERSA/V2/ViaReversaV2_Front/node_modules/reka-ui/dist/Toast/ToastTitle.js?v=c692b6b6",
      "method": "GET",
      "failure": "net::ERR_ABORTED"
    },
    {
      "url": "http://127.0.0.1:64092/_nuxt/@fs/D:/DEVJUANMARCOS/PROJETOS/KEENER/VIA%20REVERSA/V2/ViaReversaV2_Front/node_modules/reka-ui/dist/Editable/EditableSubmitTrigger.js?v=c692b6b6",
      "method": "GET",
      "failure": "net::ERR_ABORTED"
    },
    {
      "url": "http://127.0.0.1:64092/_nuxt/@fs/D:/DEVJUANMARCOS/PROJETOS/KEENER/VIA%20REVERSA/V2/ViaReversaV2_Front/node_modules/reka-ui/dist/ScrollArea/utils.js?v=c692b6b6",
      "method": "GET",
      "failure": "net::ERR_ABORTED"
    },
    {
      "url": "http://127.0.0.1:64092/_nuxt/@fs/D:/DEVJUANMARCOS/PROJETOS/KEENER/VIA%20REVERSA/V2/ViaReversaV2_Front/node_modules/reka-ui/dist/Select/SelectViewport.js?v=c692b6b6",
      "method": "GET",
      "failure": "net::ERR_ABORTED"
    },
    {
      "url": "http://127.0.0.1:64092/_nuxt/@fs/D:/DEVJUANMARCOS/PROJETOS/KEENER/VIA%20REVERSA/V2/ViaReversaV2_Front/node_modules/reka-ui/dist/Tree/TreeVirtualizer.js?v=c692b6b6",
      "method": "GET",
      "failure": "net::ERR_ABORTED"
    },
    {
      "url": "http://127.0.0.1:64092/_nuxt/@fs/D:/DEVJUANMARCOS/PROJETOS/KEENER/VIA%20REVERSA/V2/ViaReversaV2_Front/node_modules/reka-ui/dist/Select/SelectScrollDownButton.js?v=c692b6b6",
      "method": "GET",
      "failure": "net::ERR_ABORTED"
    },
    {
      "url": "http://127.0.0.1:64092/_nuxt/@fs/D:/DEVJUANMARCOS/PROJETOS/KEENER/VIA%20REVERSA/V2/ViaReversaV2_Front/node_modules/@nuxt/ui/dist/runtime/locale/en.js?v=c692b6b6",
      "method": "GET",
      "failure": "net::ERR_ABORTED"
    },
    {
      "url": "http://127.0.0.1:64092/_nuxt/@fs/D:/DEVJUANMARCOS/PROJETOS/KEENER/VIA%20REVERSA/V2/ViaReversaV2_Front/node_modules/reka-ui/dist/YearPicker/YearPickerNext.js?v=c692b6b6",
      "method": "GET",
      "failure": "net::ERR_ABORTED"
    },
    {
      "url": "http://127.0.0.1:64092/_nuxt/@fs/D:/DEVJUANMARCOS/PROJETOS/KEENER/VIA%20REVERSA/V2/ViaReversaV2_Front/node_modules/reka-ui/dist/Tooltip/TooltipProvider.js?v=c692b6b6",
      "method": "GET",
      "failure": "net::ERR_ABORTED"
    },
    {
      "url": "http://127.0.0.1:64092/_nuxt/@fs/D:/DEVJUANMARCOS/PROJETOS/KEENER/VIA%20REVERSA/V2/ViaReversaV2_Front/node_modules/reka-ui/dist/utils/style.js?v=c692b6b6",
      "method": "GET",
      "failure": "net::ERR_ABORTED"
    },
    {
      "url": "http://127.0.0.1:64092/_nuxt/@fs/D:/DEVJUANMARCOS/PROJETOS/KEENER/VIA%20REVERSA/V2/ViaReversaV2_Front/node_modules/reka-ui/dist/MonthRangePicker/MonthRangePickerHeading.js?v=c692b6b6",
      "method": "GET",
      "failure": "net::ERR_ABORTED"
    },
    {
      "url": "http://127.0.0.1:64092/_nuxt/@fs/D:/DEVJUANMARCOS/PROJETOS/KEENER/VIA%20REVERSA/V2/ViaReversaV2_Front/node_modules/reka-ui/dist/Popover/PopoverPortal.js?v=c692b6b6",
      "method": "GET",
      "failure": "net::ERR_ABORTED"
    },
    {
      "url": "http://127.0.0.1:64092/_nuxt/@fs/D:/DEVJUANMARCOS/PROJETOS/KEENER/VIA%20REVERSA/V2/ViaReversaV2_Front/node_modules/reka-ui/dist/utils/debounce.js?v=c692b6b6",
      "method": "GET",
      "failure": "net::ERR_ABORTED"
    },
    {
      "url": "http://127.0.0.1:64092/_nuxt/@fs/D:/DEVJUANMARCOS/PROJETOS/KEENER/VIA%20REVERSA/V2/ViaReversaV2_Front/node_modules/reka-ui/dist/Menubar/MenubarCheckboxItem.js?v=c692b6b6",
      "method": "GET",
      "failure": "net::ERR_ABORTED"
    },
    {
      "url": "http://127.0.0.1:64092/_nuxt/@fs/D:/DEVJUANMARCOS/PROJETOS/KEENER/VIA%20REVERSA/V2/ViaReversaV2_Front/node_modules/reka-ui/dist/Select/SelectLabel.js?v=c692b6b6",
      "method": "GET",
      "failure": "net::ERR_ABORTED"
    },
    {
      "url": "http://127.0.0.1:64092/_nuxt/@fs/D:/DEVJUANMARCOS/PROJETOS/KEENER/VIA%20REVERSA/V2/ViaReversaV2_Front/node_modules/reka-ui/dist/TimeField/TimeFieldRoot.js?v=c692b6b6",
      "method": "GET",
      "failure": "net::ERR_ABORTED"
    },
    {
      "url": "http://127.0.0.1:64092/_nuxt/@fs/D:/DEVJUANMARCOS/PROJETOS/KEENER/VIA%20REVERSA/V2/ViaReversaV2_Front/node_modules/reka-ui/dist/Select/SelectArrow.js?v=c692b6b6",
      "method": "GET",
      "failure": "net::ERR_ABORTED"
    },
    {
      "url": "http://127.0.0.1:64092/_nuxt/@fs/D:/DEVJUANMARCOS/PROJETOS/KEENER/VIA%20REVERSA/V2/ViaReversaV2_Front/node_modules/reka-ui/dist/Tree/TreeItem.js?v=c692b6b6",
      "method": "GET",
      "failure": "net::ERR_ABORTED"
    },
    {
      "url": "http://127.0.0.1:64092/_nuxt/@fs/D:/DEVJUANMARCOS/PROJETOS/KEENER/VIA%20REVERSA/V2/ViaReversaV2_Front/node_modules/reka-ui/dist/ToggleGroup/ToggleGroupItem.js?v=c692b6b6",
      "method": "GET",
      "failure": "net::ERR_ABORTED"
    },
    {
      "url": "http://127.0.0.1:64092/_nuxt/@fs/D:/DEVJUANMARCOS/PROJETOS/KEENER/VIA%20REVERSA/V2/ViaReversaV2_Front/node_modules/reka-ui/dist/ScrollArea/ScrollAreaThumb.js?v=c692b6b6",
      "method": "GET",
      "failure": "net::ERR_ABORTED"
    },
    {
      "url": "http://127.0.0.1:64092/_nuxt/@fs/D:/DEVJUANMARCOS/PROJETOS/KEENER/VIA%20REVERSA/V2/ViaReversaV2_Front/node_modules/reka-ui/dist/NavigationMenu/NavigationMenuContentImpl.js?v=c692b6b6",
      "method": "GET",
      "failure": "net::ERR_ABORTED"
    },
    {
      "url": "http://127.0.0.1:64092/_nuxt/@fs/D:/DEVJUANMARCOS/PROJETOS/KEENER/VIA%20REVERSA/V2/ViaReversaV2_Front/node_modules/reka-ui/dist/RangeCalendar/RangeCalendarHeadCell.js?v=c692b6b6",
      "method": "GET",
      "failure": "net::ERR_ABORTED"
    },
    {
      "url": "http://127.0.0.1:64092/_nuxt/@fs/D:/DEVJUANMARCOS/PROJETOS/KEENER/VIA%20REVERSA/V2/ViaReversaV2_Front/node_modules/reka-ui/dist/YearRangePicker/YearRangePickerPrev.js?v=c692b6b6",
      "method": "GET",
      "failure": "net::ERR_ABORTED"
    },
    {
      "url": "http://127.0.0.1:64092/_nuxt/@fs/D:/DEVJUANMARCOS/PROJETOS/KEENER/VIA%20REVERSA/V2/ViaReversaV2_Front/node_modules/@nuxt/ui/dist/runtime/utils/tv.js?v=c692b6b6",
      "method": "GET",
      "failure": "net::ERR_ABORTED"
    },
    {
      "url": "http://127.0.0.1:64092/_nuxt/@fs/D:/DEVJUANMARCOS/PROJETOS/KEENER/VIA%20REVERSA/V2/ViaReversaV2_Front/node_modules/reka-ui/dist/Tooltip/TooltipTrigger.js?v=c692b6b6",
      "method": "GET",
      "failure": "net::ERR_ABORTED"
    },
    {
      "url": "http://127.0.0.1:64092/_nuxt/@fs/D:/DEVJUANMARCOS/PROJETOS/KEENER/VIA%20REVERSA/V2/ViaReversaV2_Front/node_modules/reka-ui/dist/NumberField/NumberFieldInput.js?v=c692b6b6",
      "method": "GET",
      "failure": "net::ERR_ABORTED"
    },
    {
      "url": "http://127.0.0.1:64092/_nuxt/@fs/D:/DEVJUANMARCOS/PROJETOS/KEENER/VIA%20REVERSA/V2/ViaReversaV2_Front/node_modules/reka-ui/dist/MonthPicker/MonthPickerHeading.js?v=c692b6b6",
      "method": "GET",
      "failure": "net::ERR_ABORTED"
    },
    {
      "url": "http://127.0.0.1:64092/_nuxt/@fs/D:/DEVJUANMARCOS/PROJETOS/KEENER/VIA%20REVERSA/V2/ViaReversaV2_Front/node_modules/reka-ui/dist/Tooltip/TooltipRoot.js?v=c692b6b6",
      "method": "GET",
      "failure": "net::ERR_ABORTED"
    },
    {
      "url": "http://127.0.0.1:64092/_nuxt/@fs/D:/DEVJUANMARCOS/PROJETOS/KEENER/VIA%20REVERSA/V2/ViaReversaV2_Front/node_modules/reka-ui/dist/NavigationMenu/NavigationMenuIndicator.js?v=c692b6b6",
      "method": "GET",
      "failure": "net::ERR_ABORTED"
    },
    {
      "url": "http://127.0.0.1:64092/_nuxt/@fs/D:/DEVJUANMARCOS/PROJETOS/KEENER/VIA%20REVERSA/V2/ViaReversaV2_Front/node_modules/reka-ui/dist/ScrollArea/ScrollAreaScrollbarScroll.js?v=c692b6b6",
      "method": "GET",
      "failure": "net::ERR_ABORTED"
    },
    {
      "url": "http://127.0.0.1:64092/_nuxt/@fs/D:/DEVJUANMARCOS/PROJETOS/KEENER/VIA%20REVERSA/V2/ViaReversaV2_Front/node_modules/reka-ui/dist/Switch/SwitchRoot.js?v=c692b6b6",
      "method": "GET",
      "failure": "net::ERR_ABORTED"
    },
    {
      "url": "http://127.0.0.1:64092/_nuxt/@fs/D:/DEVJUANMARCOS/PROJETOS/KEENER/VIA%20REVERSA/V2/ViaReversaV2_Front/node_modules/reka-ui/dist/YearPicker/YearPickerPrev.js?v=c692b6b6",
      "method": "GET",
      "failure": "net::ERR_ABORTED"
    },
    {
      "url": "http://127.0.0.1:64092/_nuxt/@fs/D:/DEVJUANMARCOS/PROJETOS/KEENER/VIA%20REVERSA/V2/ViaReversaV2_Front/node_modules/reka-ui/dist/NavigationMenu/NavigationMenuLink.js?v=c692b6b6",
      "method": "GET",
      "failure": "net::ERR_ABORTED"
    },
    {
      "url": "http://127.0.0.1:64092/_nuxt/@fs/D:/DEVJUANMARCOS/PROJETOS/KEENER/VIA%20REVERSA/V2/ViaReversaV2_Front/node_modules/reka-ui/dist/Select/SelectSeparator.js?v=c692b6b6",
      "method": "GET",
      "failure": "net::ERR_ABORTED"
    },
    {
      "url": "http://127.0.0.1:64092/_nuxt/@fs/D:/DEVJUANMARCOS/PROJETOS/KEENER/VIA%20REVERSA/V2/ViaReversaV2_Front/node_modules/reka-ui/dist/RangeCalendar/RangeCalendarCellTrigger.js?v=c692b6b6",
      "method": "GET",
      "failure": "net::ERR_ABORTED"
    },
    {
      "url": "http://127.0.0.1:64092/_nuxt/@fs/D:/DEVJUANMARCOS/PROJETOS/KEENER/VIA%20REVERSA/V2/ViaReversaV2_Front/node_modules/reka-ui/dist/ScrollArea/ScrollAreaScrollbarY.js?v=c692b6b6",
      "method": "GET",
      "failure": "net::ERR_ABORTED"
    },
    {
      "url": "http://127.0.0.1:64092/_nuxt/@fs/D:/DEVJUANMARCOS/PROJETOS/KEENER/VIA%20REVERSA/V2/ViaReversaV2_Front/node_modules/reka-ui/dist/Toolbar/ToolbarLink.js?v=c692b6b6",
      "method": "GET",
      "failure": "net::ERR_ABORTED"
    },
    {
      "url": "http://127.0.0.1:64092/_nuxt/@fs/D:/DEVJUANMARCOS/PROJETOS/KEENER/VIA%20REVERSA/V2/ViaReversaV2_Front/node_modules/reka-ui/dist/HoverCard/HoverCardContentImpl.js?v=c692b6b6",
      "method": "GET",
      "failure": "net::ERR_ABORTED"
    },
    {
      "url": "http://127.0.0.1:64092/_nuxt/@fs/D:/DEVJUANMARCOS/PROJETOS/KEENER/VIA%20REVERSA/V2/ViaReversaV2_Front/node_modules/reka-ui/dist/YearRangePicker/YearRangePickerNext.js?v=c692b6b6",
      "method": "GET",
      "failure": "net::ERR_ABORTED"
    },
    {
      "url": "http://127.0.0.1:64092/_nuxt/@fs/D:/DEVJUANMARCOS/PROJETOS/KEENER/VIA%20REVERSA/V2/ViaReversaV2_Front/node_modules/reka-ui/dist/Pagination/PaginationNext.js?v=c692b6b6",
      "method": "GET",
      "failure": "net::ERR_ABORTED"
    },
    {
      "url": "http://127.0.0.1:64092/_nuxt/@fs/D:/DEVJUANMARCOS/PROJETOS/KEENER/VIA%20REVERSA/V2/ViaReversaV2_Front/node_modules/reka-ui/dist/ScrollArea/ScrollAreaScrollbarAuto.js?v=c692b6b6",
      "method": "GET",
      "failure": "net::ERR_ABORTED"
    },
    {
      "url": "http://127.0.0.1:64092/_nuxt/@fs/D:/DEVJUANMARCOS/PROJETOS/KEENER/VIA%20REVERSA/V2/ViaReversaV2_Front/node_modules/reka-ui/dist/Tooltip/TooltipContent.js?v=c692b6b6",
      "method": "GET",
      "failure": "net::ERR_ABORTED"
    },
    {
      "url": "http://127.0.0.1:64092/_nuxt/@fs/D:/DEVJUANMARCOS/PROJETOS/KEENER/VIA%20REVERSA/V2/ViaReversaV2_Front/node_modules/reka-ui/dist/utils/resizePanel.js?v=c692b6b6",
      "method": "GET",
      "failure": "net::ERR_ABORTED"
    },
    {
      "url": "http://127.0.0.1:64092/_nuxt/@fs/D:/DEVJUANMARCOS/PROJETOS/KEENER/VIA%20REVERSA/V2/ViaReversaV2_Front/node_modules/ohash/dist/index.mjs?v=c692b6b6",
      "method": "GET",
      "failure": "net::ERR_ABORTED"
    },
    {
      "url": "http://127.0.0.1:64092/_nuxt/@fs/D:/DEVJUANMARCOS/PROJETOS/KEENER/VIA%20REVERSA/V2/ViaReversaV2_Front/node_modules/reka-ui/dist/YearPicker/YearPickerGridBody.js?v=c692b6b6",
      "method": "GET",
      "failure": "net::ERR_ABORTED"
    },
    {
      "url": "http://127.0.0.1:64092/_nuxt/@fs/D:/DEVJUANMARCOS/PROJETOS/KEENER/VIA%20REVERSA/V2/ViaReversaV2_Front/node_modules/reka-ui/dist/RadioGroup/Radio.js?v=c692b6b6",
      "method": "GET",
      "failure": "net::ERR_ABORTED"
    },
    {
      "url": "http://127.0.0.1:64092/_nuxt/@fs/D:/DEVJUANMARCOS/PROJETOS/KEENER/VIA%20REVERSA/V2/ViaReversaV2_Front/node_modules/reka-ui/dist/MonthPicker/MonthPickerNext.js?v=c692b6b6",
      "method": "GET",
      "failure": "net::ERR_ABORTED"
    },
    {
      "url": "http://127.0.0.1:64092/_nuxt/@fs/D:/DEVJUANMARCOS/PROJETOS/KEENER/VIA%20REVERSA/V2/ViaReversaV2_Front/node_modules/reka-ui/dist/NavigationMenu/NavigationMenuList.js?v=c692b6b6",
      "method": "GET",
      "failure": "net::ERR_ABORTED"
    },
    {
      "url": "http://127.0.0.1:64092/_nuxt/@fs/D:/DEVJUANMARCOS/PROJETOS/KEENER/VIA%20REVERSA/V2/ViaReversaV2_Front/node_modules/reka-ui/dist/TimeField/TimeFieldInput.js?v=c692b6b6",
      "method": "GET",
      "failure": "net::ERR_ABORTED"
    },
    {
      "url": "http://127.0.0.1:64092/_nuxt/@fs/D:/DEVJUANMARCOS/PROJETOS/KEENER/VIA%20REVERSA/V2/ViaReversaV2_Front/node_modules/reka-ui/dist/Tabs/utils.js?v=c692b6b6",
      "method": "GET",
      "failure": "net::ERR_ABORTED"
    },
    {
      "url": "http://127.0.0.1:64092/_nuxt/@fs/D:/DEVJUANMARCOS/PROJETOS/KEENER/VIA%20REVERSA/V2/ViaReversaV2_Front/node_modules/reka-ui/dist/Pagination/PaginationListItem.js?v=c692b6b6",
      "method": "GET",
      "failure": "net::ERR_ABORTED"
    },
    {
      "url": "http://127.0.0.1:64092/_nuxt/@fs/D:/DEVJUANMARCOS/PROJETOS/KEENER/VIA%20REVERSA/V2/ViaReversaV2_Front/node_modules/reka-ui/dist/Menubar/MenubarTrigger.js?v=c692b6b6",
      "method": "GET",
      "failure": "net::ERR_ABORTED"
    },
    {
      "url": "http://127.0.0.1:64092/_nuxt/@fs/D:/DEVJUANMARCOS/PROJETOS/KEENER/VIA%20REVERSA/V2/ViaReversaV2_Front/node_modules/reka-ui/dist/RadioGroup/RadioGroupItem.js?v=c692b6b6",
      "method": "GET",
      "failure": "net::ERR_ABORTED"
    },
    {
      "url": "http://127.0.0.1:64092/_nuxt/@fs/D:/DEVJUANMARCOS/PROJETOS/KEENER/VIA%20REVERSA/V2/ViaReversaV2_Front/node_modules/reka-ui/dist/Pagination/PaginationLast.js?v=c692b6b6",
      "method": "GET",
      "failure": "net::ERR_ABORTED"
    },
    {
      "url": "http://127.0.0.1:64092/_nuxt/@fs/D:/DEVJUANMARCOS/PROJETOS/KEENER/VIA%20REVERSA/V2/ViaReversaV2_Front/node_modules/reka-ui/dist/YearPicker/YearPickerRoot.js?v=c692b6b6",
      "method": "GET",
      "failure": "net::ERR_ABORTED"
    },
    {
      "url": "http://127.0.0.1:64092/_nuxt/@fs/D:/DEVJUANMARCOS/PROJETOS/KEENER/VIA%20REVERSA/V2/ViaReversaV2_Front/node_modules/reka-ui/dist/MonthRangePicker/MonthRangePickerGridRow.js?v=c692b6b6",
      "method": "GET",
      "failure": "net::ERR_ABORTED"
    },
    {
      "url": "http://127.0.0.1:64092/_nuxt/@fs/D:/DEVJUANMARCOS/PROJETOS/KEENER/VIA%20REVERSA/V2/ViaReversaV2_Front/node_modules/reka-ui/dist/Toast/ToastPortal.js?v=c692b6b6",
      "method": "GET",
      "failure": "net::ERR_ABORTED"
    },
    {
      "url": "http://127.0.0.1:64092/_nuxt/@fs/D:/DEVJUANMARCOS/PROJETOS/KEENER/VIA%20REVERSA/V2/ViaReversaV2_Front/node_modules/reka-ui/dist/NumberField/NumberFieldDecrement.js?v=c692b6b6",
      "method": "GET",
      "failure": "net::ERR_ABORTED"
    },
    {
      "url": "http://127.0.0.1:64092/_nuxt/@fs/D:/DEVJUANMARCOS/PROJETOS/KEENER/VIA%20REVERSA/V2/ViaReversaV2_Front/node_modules/reka-ui/dist/utils/stackingOrder.js?v=c692b6b6",
      "method": "GET",
      "failure": "net::ERR_ABORTED"
    },
    {
      "url": "http://127.0.0.1:64092/_nuxt/@fs/D:/DEVJUANMARCOS/PROJETOS/KEENER/VIA%20REVERSA/V2/ViaReversaV2_Front/node_modules/reka-ui/dist/MonthPicker/MonthPickerCellTrigger.js?v=c692b6b6",
      "method": "GET",
      "failure": "net::ERR_ABORTED"
    },
    {
      "url": "http://127.0.0.1:64092/_nuxt/@fs/D:/DEVJUANMARCOS/PROJETOS/KEENER/VIA%20REVERSA/V2/ViaReversaV2_Front/node_modules/reka-ui/dist/Toast/FocusProxy.js?v=c692b6b6",
      "method": "GET",
      "failure": "net::ERR_ABORTED"
    },
    {
      "url": "http://127.0.0.1:64092/_nuxt/@fs/D:/DEVJUANMARCOS/PROJETOS/KEENER/VIA%20REVERSA/V2/ViaReversaV2_Front/node_modules/reka-ui/dist/Stepper/StepperItem.js?v=c692b6b6",
      "method": "GET",
      "failure": "net::ERR_ABORTED"
    },
    {
      "url": "http://127.0.0.1:64092/_nuxt/@fs/D:/DEVJUANMARCOS/PROJETOS/KEENER/VIA%20REVERSA/V2/ViaReversaV2_Front/node_modules/reka-ui/dist/Tree/utils.js?v=c692b6b6",
      "method": "GET",
      "failure": "net::ERR_ABORTED"
    },
    {
      "url": "http://127.0.0.1:64092/_nuxt/@fs/D:/DEVJUANMARCOS/PROJETOS/KEENER/VIA%20REVERSA/V2/ViaReversaV2_Front/node_modules/reka-ui/dist/NavigationMenu/NavigationMenuSub.js?v=c692b6b6",
      "method": "GET",
      "failure": "net::ERR_ABORTED"
    },
    {
      "url": "http://127.0.0.1:64092/_nuxt/@fs/D:/DEVJUANMARCOS/PROJETOS/KEENER/VIA%20REVERSA/V2/ViaReversaV2_Front/node_modules/reka-ui/dist/Select/SelectTrigger.js?v=c692b6b6",
      "method": "GET",
      "failure": "net::ERR_ABORTED"
    },
    {
      "url": "http://127.0.0.1:64092/_nuxt/@fs/D:/DEVJUANMARCOS/PROJETOS/KEENER/VIA%20REVERSA/V2/ViaReversaV2_Front/node_modules/reka-ui/dist/MonthRangePicker/MonthRangePickerHeader.js?v=c692b6b6",
      "method": "GET",
      "failure": "net::ERR_ABORTED"
    },
    {
      "url": "http://127.0.0.1:64092/_nuxt/@fs/D:/DEVJUANMARCOS/PROJETOS/KEENER/VIA%20REVERSA/V2/ViaReversaV2_Front/node_modules/reka-ui/dist/utils/units.js?v=c692b6b6",
      "method": "GET",
      "failure": "net::ERR_ABORTED"
    },
    {
      "url": "http://127.0.0.1:64092/_nuxt/@fs/D:/DEVJUANMARCOS/PROJETOS/KEENER/VIA%20REVERSA/V2/ViaReversaV2_Front/node_modules/reka-ui/dist/RangeCalendar/RangeCalendarGridHead.js?v=c692b6b6",
      "method": "GET",
      "failure": "net::ERR_ABORTED"
    },
    {
      "url": "http://127.0.0.1:64092/_nuxt/@fs/D:/DEVJUANMARCOS/PROJETOS/KEENER/VIA%20REVERSA/V2/ViaReversaV2_Front/node_modules/reka-ui/dist/Pagination/PaginationPrev.js?v=c692b6b6",
      "method": "GET",
      "failure": "net::ERR_ABORTED"
    },
    {
      "url": "http://127.0.0.1:64092/_nuxt/@fs/D:/DEVJUANMARCOS/PROJETOS/KEENER/VIA%20REVERSA/V2/ViaReversaV2_Front/node_modules/reka-ui/dist/HoverCard/HoverCardPortal.js?v=c692b6b6",
      "method": "GET",
      "failure": "net::ERR_ABORTED"
    },
    {
      "url": "http://127.0.0.1:64092/_nuxt/@fs/D:/DEVJUANMARCOS/PROJETOS/KEENER/VIA%20REVERSA/V2/ViaReversaV2_Front/node_modules/reka-ui/dist/utils/validation.js?v=c692b6b6",
      "method": "GET",
      "failure": "net::ERR_ABORTED"
    },
    {
      "url": "http://127.0.0.1:64092/_nuxt/@fs/D:/DEVJUANMARCOS/PROJETOS/KEENER/VIA%20REVERSA/V2/ViaReversaV2_Front/node_modules/reka-ui/dist/ScrollArea/ScrollAreaViewport.js?v=c692b6b6",
      "method": "GET",
      "failure": "net::ERR_ABORTED"
    },
    {
      "url": "http://127.0.0.1:64092/_nuxt/@fs/D:/DEVJUANMARCOS/PROJETOS/KEENER/VIA%20REVERSA/V2/ViaReversaV2_Front/node_modules/reka-ui/dist/Select/SelectScrollUpButton.js?v=c692b6b6",
      "method": "GET",
      "failure": "net::ERR_ABORTED"
    },
    {
      "url": "http://127.0.0.1:64092/_nuxt/@fs/D:/DEVJUANMARCOS/PROJETOS/KEENER/VIA%20REVERSA/V2/ViaReversaV2_Front/node_modules/reka-ui/dist/ScrollArea/ScrollAreaScrollbarGlimpse.js?v=c692b6b6",
      "method": "GET",
      "failure": "net::ERR_ABORTED"
    },
    {
      "url": "http://127.0.0.1:64092/_nuxt/@fs/D:/DEVJUANMARCOS/PROJETOS/KEENER/VIA%20REVERSA/V2/ViaReversaV2_Front/node_modules/reka-ui/dist/Stepper/StepperDescription.js?v=c692b6b6",
      "method": "GET",
      "failure": "net::ERR_ABORTED"
    },
    {
      "url": "http://127.0.0.1:64092/_nuxt/@fs/D:/DEVJUANMARCOS/PROJETOS/KEENER/VIA%20REVERSA/V2/ViaReversaV2_Front/node_modules/reka-ui/dist/Splitter/SplitterPanel.js?v=c692b6b6",
      "method": "GET",
      "failure": "net::ERR_ABORTED"
    },
    {
      "url": "http://127.0.0.1:64092/_nuxt/@fs/D:/DEVJUANMARCOS/PROJETOS/KEENER/VIA%20REVERSA/V2/ViaReversaV2_Front/node_modules/reka-ui/dist/Menubar/MenubarLabel.js?v=c692b6b6",
      "method": "GET",
      "failure": "net::ERR_ABORTED"
    },
    {
      "url": "http://127.0.0.1:64092/_nuxt/@fs/D:/DEVJUANMARCOS/PROJETOS/KEENER/VIA%20REVERSA/V2/ViaReversaV2_Front/node_modules/reka-ui/dist/HoverCard/HoverCardContent.js?v=c692b6b6",
      "method": "GET",
      "failure": "net::ERR_ABORTED"
    },
    {
      "url": "http://127.0.0.1:64092/_nuxt/@fs/D:/DEVJUANMARCOS/PROJETOS/KEENER/VIA%20REVERSA/V2/ViaReversaV2_Front/node_modules/reka-ui/dist/RangeCalendar/RangeCalendarGridBody.js?v=c692b6b6",
      "method": "GET",
      "failure": "net::ERR_ABORTED"
    },
    {
      "url": "http://127.0.0.1:64092/_nuxt/@fs/D:/DEVJUANMARCOS/PROJETOS/KEENER/VIA%20REVERSA/V2/ViaReversaV2_Front/node_modules/reka-ui/dist/Tabs/TabsContent.js?v=c692b6b6",
      "method": "GET",
      "failure": "net::ERR_ABORTED"
    },
    {
      "url": "http://127.0.0.1:64092/_nuxt/@fs/D:/DEVJUANMARCOS/PROJETOS/KEENER/VIA%20REVERSA/V2/ViaReversaV2_Front/node_modules/reka-ui/dist/Stepper/StepperIndicator.js?v=c692b6b6",
      "method": "GET",
      "failure": "net::ERR_ABORTED"
    },
    {
      "url": "http://127.0.0.1:64092/_nuxt/@fs/D:/DEVJUANMARCOS/PROJETOS/KEENER/VIA%20REVERSA/V2/ViaReversaV2_Front/node_modules/reka-ui/dist/Menubar/MenubarSubContent.js?v=c692b6b6",
      "method": "GET",
      "failure": "net::ERR_ABORTED"
    },
    {
      "url": "http://127.0.0.1:64092/_nuxt/@fs/D:/DEVJUANMARCOS/PROJETOS/KEENER/VIA%20REVERSA/V2/ViaReversaV2_Front/node_modules/aria-hidden/dist/es2015/index.js?v=c692b6b6",
      "method": "GET",
      "failure": "net::ERR_ABORTED"
    },
    {
      "url": "http://127.0.0.1:64092/_nuxt/@fs/D:/DEVJUANMARCOS/PROJETOS/KEENER/VIA%20REVERSA/V2/ViaReversaV2_Front/node_modules/reka-ui/dist/Menubar/MenubarSub.js?v=c692b6b6",
      "method": "GET",
      "failure": "net::ERR_ABORTED"
    },
    {
      "url": "http://127.0.0.1:64092/_nuxt/@fs/D:/DEVJUANMARCOS/PROJETOS/KEENER/VIA%20REVERSA/V2/ViaReversaV2_Front/node_modules/reka-ui/dist/YearPicker/YearPickerCellTrigger.js?v=c692b6b6",
      "method": "GET",
      "failure": "net::ERR_ABORTED"
    },
    {
      "url": "http://127.0.0.1:64092/_nuxt/@fs/D:/DEVJUANMARCOS/PROJETOS/KEENER/VIA%20REVERSA/V2/ViaReversaV2_Front/node_modules/reka-ui/dist/YearPicker/YearPickerHeader.js?v=c692b6b6",
      "method": "GET",
      "failure": "net::ERR_ABORTED"
    },
    {
      "url": "http://127.0.0.1:64092/_nuxt/@fs/D:/DEVJUANMARCOS/PROJETOS/KEENER/VIA%20REVERSA/V2/ViaReversaV2_Front/node_modules/reka-ui/dist/Toast/utils.js?v=c692b6b6",
      "method": "GET",
      "failure": "net::ERR_ABORTED"
    },
    {
      "url": "http://127.0.0.1:64092/_nuxt/@fs/D:/DEVJUANMARCOS/PROJETOS/KEENER/VIA%20REVERSA/V2/ViaReversaV2_Front/node_modules/reka-ui/dist/Pagination/PaginationFirst.js?v=c692b6b6",
      "method": "GET",
      "failure": "net::ERR_ABORTED"
    },
    {
      "url": "http://127.0.0.1:64092/_nuxt/@fs/D:/DEVJUANMARCOS/PROJETOS/KEENER/VIA%20REVERSA/V2/ViaReversaV2_Front/node_modules/reka-ui/dist/Select/SelectItem.js?v=c692b6b6",
      "method": "GET",
      "failure": "net::ERR_ABORTED"
    },
    {
      "url": "http://127.0.0.1:64092/_nuxt/@fs/D:/DEVJUANMARCOS/PROJETOS/KEENER/VIA%20REVERSA/V2/ViaReversaV2_Front/node_modules/reka-ui/dist/Tabs/TabsTrigger.js?v=c692b6b6",
      "method": "GET",
      "failure": "net::ERR_ABORTED"
    },
    {
      "url": "http://127.0.0.1:64092/_nuxt/@fs/D:/DEVJUANMARCOS/PROJETOS/KEENER/VIA%20REVERSA/V2/ViaReversaV2_Front/node_modules/reka-ui/dist/Select/SelectItemIndicator.js?v=c692b6b6",
      "method": "GET",
      "failure": "net::ERR_ABORTED"
    },
    {
      "url": "http://127.0.0.1:64092/_nuxt/@fs/D:/DEVJUANMARCOS/PROJETOS/KEENER/VIA%20REVERSA/V2/ViaReversaV2_Front/node_modules/reka-ui/dist/ScrollArea/ScrollAreaCornerImpl.js?v=c692b6b6",
      "method": "GET",
      "failure": "net::ERR_ABORTED"
    },
    {
      "url": "http://127.0.0.1:64092/_nuxt/@fs/D:/DEVJUANMARCOS/PROJETOS/KEENER/VIA%20REVERSA/V2/ViaReversaV2_Front/node_modules/reka-ui/dist/utils/calculate.js?v=c692b6b6",
      "method": "GET",
      "failure": "net::ERR_ABORTED"
    },
    {
      "url": "http://127.0.0.1:64092/_nuxt/@fs/D:/DEVJUANMARCOS/PROJETOS/KEENER/VIA%20REVERSA/V2/ViaReversaV2_Front/node_modules/reka-ui/dist/composables/useWindowSplitterPanelGroupBehavior.js?v=c692b6b6",
      "method": "GET",
      "failure": "net::ERR_ABORTED"
    },
    {
      "url": "http://127.0.0.1:64092/_nuxt/@fs/D:/DEVJUANMARCOS/PROJETOS/KEENER/VIA%20REVERSA/V2/ViaReversaV2_Front/node_modules/reka-ui/dist/Splitter/SplitterGroup.js?v=c692b6b6",
      "method": "GET",
      "failure": "net::ERR_ABORTED"
    },
    {
      "url": "http://127.0.0.1:64092/_nuxt/@fs/D:/DEVJUANMARCOS/PROJETOS/KEENER/VIA%20REVERSA/V2/ViaReversaV2_Front/node_modules/reka-ui/dist/YearPicker/YearPickerGridRow.js?v=c692b6b6",
      "method": "GET",
      "failure": "net::ERR_ABORTED"
    },
    {
      "url": "http://127.0.0.1:64092/_nuxt/@fs/D:/DEVJUANMARCOS/PROJETOS/KEENER/VIA%20REVERSA/V2/ViaReversaV2_Front/node_modules/reka-ui/dist/Toast/ToastAction.js?v=c692b6b6",
      "method": "GET",
      "failure": "net::ERR_ABORTED"
    },
    {
      "url": "http://127.0.0.1:64092/_nuxt/@fs/D:/DEVJUANMARCOS/PROJETOS/KEENER/VIA%20REVERSA/V2/ViaReversaV2_Front/node_modules/reka-ui/dist/ScrollArea/ScrollAreaScrollbarX.js?v=c692b6b6",
      "method": "GET",
      "failure": "net::ERR_ABORTED"
    },
    {
      "url": "http://127.0.0.1:64092/_nuxt/@fs/D:/DEVJUANMARCOS/PROJETOS/KEENER/VIA%20REVERSA/V2/ViaReversaV2_Front/node_modules/reka-ui/dist/Menubar/MenubarRadioGroup.js?v=c692b6b6",
      "method": "GET",
      "failure": "net::ERR_ABORTED"
    },
    {
      "url": "http://127.0.0.1:64092/_nuxt/@fs/D:/DEVJUANMARCOS/PROJETOS/KEENER/VIA%20REVERSA/V2/ViaReversaV2_Front/node_modules/reka-ui/dist/TagsInput/TagsInputItem.js?v=c692b6b6",
      "method": "GET",
      "failure": "net::ERR_ABORTED"
    },
    {
      "url": "http://127.0.0.1:64092/_nuxt/@fs/D:/DEVJUANMARCOS/PROJETOS/KEENER/VIA%20REVERSA/V2/ViaReversaV2_Front/node_modules/reka-ui/dist/Editable/EditableCancelTrigger.js?v=c692b6b6",
      "method": "GET",
      "failure": "net::ERR_ABORTED"
    },
    {
      "url": "http://127.0.0.1:64092/_nuxt/@fs/D:/DEVJUANMARCOS/PROJETOS/KEENER/VIA%20REVERSA/V2/ViaReversaV2_Front/node_modules/reka-ui/dist/Toast/ToastClose.js?v=c692b6b6",
      "method": "GET",
      "failure": "net::ERR_ABORTED"
    },
    {
      "url": "http://127.0.0.1:64092/_nuxt/@fs/D:/DEVJUANMARCOS/PROJETOS/KEENER/VIA%20REVERSA/V2/ViaReversaV2_Front/node_modules/reka-ui/dist/Stepper/StepperSeparator.js?v=c692b6b6",
      "method": "GET",
      "failure": "net::ERR_ABORTED"
    },
    {
      "url": "http://127.0.0.1:64092/_nuxt/@fs/D:/DEVJUANMARCOS/PROJETOS/KEENER/VIA%20REVERSA/V2/ViaReversaV2_Front/node_modules/reka-ui/dist/TagsInput/TagsInputItemText.js?v=c692b6b6",
      "method": "GET",
      "failure": "net::ERR_ABORTED"
    },
    {
      "url": "http://127.0.0.1:64092/_nuxt/@fs/D:/DEVJUANMARCOS/PROJETOS/KEENER/VIA%20REVERSA/V2/ViaReversaV2_Front/node_modules/reka-ui/dist/Popover/PopoverArrow.js?v=c692b6b6",
      "method": "GET",
      "failure": "net::ERR_ABORTED"
    },
    {
      "url": "http://127.0.0.1:64092/_nuxt/@fs/D:/DEVJUANMARCOS/PROJETOS/KEENER/VIA%20REVERSA/V2/ViaReversaV2_Front/node_modules/reka-ui/dist/ScrollArea/ScrollAreaScrollbar.js?v=c692b6b6",
      "method": "GET",
      "failure": "net::ERR_ABORTED"
    },
    {
      "url": "http://127.0.0.1:64092/_nuxt/@fs/D:/DEVJUANMARCOS/PROJETOS/KEENER/VIA%20REVERSA/V2/ViaReversaV2_Front/node_modules/reka-ui/dist/Stepper/StepperTitle.js?v=c692b6b6",
      "method": "GET",
      "failure": "net::ERR_ABORTED"
    },
    {
      "url": "http://127.0.0.1:64092/_nuxt/@fs/D:/DEVJUANMARCOS/PROJETOS/KEENER/VIA%20REVERSA/V2/ViaReversaV2_Front/node_modules/reka-ui/dist/Menubar/MenubarArrow.js?v=c692b6b6",
      "method": "GET",
      "failure": "net::ERR_ABORTED"
    },
    {
      "url": "http://127.0.0.1:64092/_nuxt/@fs/D:/DEVJUANMARCOS/PROJETOS/KEENER/VIA%20REVERSA/V2/ViaReversaV2_Front/node_modules/reka-ui/dist/TagsInput/TagsInputRoot.js?v=c692b6b6",
      "method": "GET",
      "failure": "net::ERR_ABORTED"
    },
    {
      "url": "http://127.0.0.1:64092/_nuxt/@fs/D:/DEVJUANMARCOS/PROJETOS/KEENER/VIA%20REVERSA/V2/ViaReversaV2_Front/node_modules/reka-ui/dist/PinInput/PinInputInput.js?v=c692b6b6",
      "method": "GET",
      "failure": "net::ERR_ABORTED"
    },
    {
      "url": "http://127.0.0.1:64092/_nuxt/@fs/D:/DEVJUANMARCOS/PROJETOS/KEENER/VIA%20REVERSA/V2/ViaReversaV2_Front/node_modules/reka-ui/dist/TagsInput/TagsInputInput.js?v=c692b6b6",
      "method": "GET",
      "failure": "net::ERR_ABORTED"
    },
    {
      "url": "http://127.0.0.1:64092/_nuxt/@fs/D:/DEVJUANMARCOS/PROJETOS/KEENER/VIA%20REVERSA/V2/ViaReversaV2_Front/node_modules/reka-ui/dist/YearPicker/YearPickerHeading.js?v=c692b6b6",
      "method": "GET",
      "failure": "net::ERR_ABORTED"
    },
    {
      "url": "http://127.0.0.1:64092/_nuxt/@fs/D:/DEVJUANMARCOS/PROJETOS/KEENER/VIA%20REVERSA/V2/ViaReversaV2_Front/node_modules/reka-ui/dist/Popover/PopoverClose.js?v=c692b6b6",
      "method": "GET",
      "failure": "net::ERR_ABORTED"
    },
    {
      "url": "http://127.0.0.1:64092/_nuxt/@fs/D:/DEVJUANMARCOS/PROJETOS/KEENER/VIA%20REVERSA/V2/ViaReversaV2_Front/node_modules/reka-ui/dist/Popover/PopoverTrigger.js?v=c692b6b6",
      "method": "GET",
      "failure": "net::ERR_ABORTED"
    },
    {
      "url": "http://127.0.0.1:64092/_nuxt/@fs/D:/DEVJUANMARCOS/PROJETOS/KEENER/VIA%20REVERSA/V2/ViaReversaV2_Front/node_modules/reka-ui/dist/MonthRangePicker/useRangeMonthPicker.js?v=c692b6b6",
      "method": "GET",
      "failure": "net::ERR_ABORTED"
    },
    {
      "url": "http://127.0.0.1:64092/_nuxt/@fs/D:/DEVJUANMARCOS/PROJETOS/KEENER/VIA%20REVERSA/V2/ViaReversaV2_Front/node_modules/reka-ui/dist/RangeCalendar/RangeCalendarRoot.js?v=c692b6b6",
      "method": "GET",
      "failure": "net::ERR_ABORTED"
    },
    {
      "url": "http://127.0.0.1:64092/_nuxt/@fs/D:/DEVJUANMARCOS/PROJETOS/KEENER/VIA%20REVERSA/V2/ViaReversaV2_Front/node_modules/reka-ui/dist/YearRangePicker/YearRangePickerHeading.js?v=c692b6b6",
      "method": "GET",
      "failure": "net::ERR_ABORTED"
    },
    {
      "url": "http://127.0.0.1:64092/_nuxt/@fs/D:/DEVJUANMARCOS/PROJETOS/KEENER/VIA%20REVERSA/V2/ViaReversaV2_Front/node_modules/reka-ui/dist/Splitter/SplitterResizeHandle.js?v=c692b6b6",
      "method": "GET",
      "failure": "net::ERR_ABORTED"
    },
    {
      "url": "http://127.0.0.1:64092/_nuxt/@fs/D:/DEVJUANMARCOS/PROJETOS/KEENER/VIA%20REVERSA/V2/ViaReversaV2_Front/node_modules/reka-ui/dist/MonthPicker/MonthPickerHeader.js?v=c692b6b6",
      "method": "GET",
      "failure": "net::ERR_ABORTED"
    },
    {
      "url": "http://127.0.0.1:64092/_nuxt/@fs/D:/DEVJUANMARCOS/PROJETOS/KEENER/VIA%20REVERSA/V2/ViaReversaV2_Front/node_modules/reka-ui/dist/Menubar/MenubarSubTrigger.js?v=c692b6b6",
      "method": "GET",
      "failure": "net::ERR_ABORTED"
    },
    {
      "url": "http://127.0.0.1:64092/_nuxt/@fs/D:/DEVJUANMARCOS/PROJETOS/KEENER/VIA%20REVERSA/V2/ViaReversaV2_Front/node_modules/reka-ui/dist/Toast/ToastAnnounceExclude.js?v=c692b6b6",
      "method": "GET",
      "failure": "net::ERR_ABORTED"
    },
    {
      "url": "http://127.0.0.1:64092/_nuxt/@fs/D:/DEVJUANMARCOS/PROJETOS/KEENER/VIA%20REVERSA/V2/ViaReversaV2_Front/node_modules/reka-ui/dist/index2.js?v=c692b6b6",
      "method": "GET",
      "failure": "net::ERR_ABORTED"
    },
    {
      "url": "http://127.0.0.1:64092/_nuxt/@fs/D:/DEVJUANMARCOS/PROJETOS/KEENER/VIA%20REVERSA/V2/ViaReversaV2_Front/node_modules/reka-ui/dist/utils/constants.js?v=c692b6b6",
      "method": "GET",
      "failure": "net::ERR_ABORTED"
    },
    {
      "url": "http://127.0.0.1:64092/_nuxt/@fs/D:/DEVJUANMARCOS/PROJETOS/KEENER/VIA%20REVERSA/V2/ViaReversaV2_Front/node_modules/reka-ui/dist/Select/SelectIcon.js?v=c692b6b6",
      "method": "GET",
      "failure": "net::ERR_ABORTED"
    },
    {
      "url": "http://127.0.0.1:64092/_nuxt/@fs/D:/DEVJUANMARCOS/PROJETOS/KEENER/VIA%20REVERSA/V2/ViaReversaV2_Front/node_modules/reka-ui/dist/utils/compare.js?v=c692b6b6",
      "method": "GET",
      "failure": "net::ERR_ABORTED"
    },
    {
      "url": "http://127.0.0.1:64092/_nuxt/@fs/D:/DEVJUANMARCOS/PROJETOS/KEENER/VIA%20REVERSA/V2/ViaReversaV2_Front/node_modules/reka-ui/dist/MonthPicker/MonthPickerGridRow.js?v=c692b6b6",
      "method": "GET",
      "failure": "net::ERR_ABORTED"
    },
    {
      "url": "http://127.0.0.1:64092/_nuxt/@fs/D:/DEVJUANMARCOS/PROJETOS/KEENER/VIA%20REVERSA/V2/ViaReversaV2_Front/node_modules/reka-ui/dist/NavigationMenu/NavigationMenuTrigger.js?v=c692b6b6",
      "method": "GET",
      "failure": "net::ERR_ABORTED"
    },
    {
      "url": "http://127.0.0.1:64092/_nuxt/@fs/D:/DEVJUANMARCOS/PROJETOS/KEENER/VIA%20REVERSA/V2/ViaReversaV2_Front/node_modules/reka-ui/dist/Tabs/TabsList.js?v=c692b6b6",
      "method": "GET",
      "failure": "net::ERR_ABORTED"
    },
    {
      "url": "http://127.0.0.1:64092/_nuxt/@fs/D:/DEVJUANMARCOS/PROJETOS/KEENER/VIA%20REVERSA/V2/ViaReversaV2_Front/node_modules/reka-ui/dist/Popover/PopoverContentImpl.js?v=c692b6b6",
      "method": "GET",
      "failure": "net::ERR_ABORTED"
    },
    {
      "url": "http://127.0.0.1:64092/_nuxt/@fs/D:/DEVJUANMARCOS/PROJETOS/KEENER/VIA%20REVERSA/V2/ViaReversaV2_Front/node_modules/reka-ui/dist/MonthRangePicker/MonthRangePickerCellTrigger.js?v=c692b6b6",
      "method": "GET",
      "failure": "net::ERR_ABORTED"
    },
    {
      "url": "http://127.0.0.1:64092/_nuxt/@fs/D:/DEVJUANMARCOS/PROJETOS/KEENER/VIA%20REVERSA/V2/ViaReversaV2_Front/node_modules/reka-ui/dist/utils/layout.js?v=c692b6b6",
      "method": "GET",
      "failure": "net::ERR_ABORTED"
    },
    {
      "url": "http://127.0.0.1:64092/_nuxt/@fs/D:/DEVJUANMARCOS/PROJETOS/KEENER/VIA%20REVERSA/V2/ViaReversaV2_Front/node_modules/reka-ui/dist/Stepper/StepperTrigger.js?v=c692b6b6",
      "method": "GET",
      "failure": "net::ERR_ABORTED"
    },
    {
      "url": "http://127.0.0.1:64092/_nuxt/@fs/D:/DEVJUANMARCOS/PROJETOS/KEENER/VIA%20REVERSA/V2/ViaReversaV2_Front/node_modules/reka-ui/dist/HoverCard/HoverCardArrow.js?v=c692b6b6",
      "method": "GET",
      "failure": "net::ERR_ABORTED"
    },
    {
      "url": "http://127.0.0.1:64092/_nuxt/@fs/D:/DEVJUANMARCOS/PROJETOS/KEENER/VIA%20REVERSA/V2/ViaReversaV2_Front/node_modules/reka-ui/dist/Select/SelectScrollButtonImpl.js?v=c692b6b6",
      "method": "GET",
      "failure": "net::ERR_ABORTED"
    },
    {
      "url": "http://127.0.0.1:64092/_nuxt/@fs/D:/DEVJUANMARCOS/PROJETOS/KEENER/VIA%20REVERSA/V2/ViaReversaV2_Front/node_modules/reka-ui/dist/ScrollArea/ScrollAreaRoot.js?v=c692b6b6",
      "method": "GET",
      "failure": "net::ERR_ABORTED"
    },
    {
      "url": "http://127.0.0.1:64092/_nuxt/@fs/D:/DEVJUANMARCOS/PROJETOS/KEENER/VIA%20REVERSA/V2/ViaReversaV2_Front/node_modules/@nuxt/ui/dist/runtime/components/Toast.vue",
      "method": "GET",
      "failure": "net::ERR_ABORTED"
    },
    {
      "url": "http://127.0.0.1:64092/_nuxt/@fs/D:/DEVJUANMARCOS/PROJETOS/KEENER/VIA%20REVERSA/V2/ViaReversaV2_Front/node_modules/reka-ui/dist/ScrollArea/ScrollAreaCorner.js?v=c692b6b6",
      "method": "GET",
      "failure": "net::ERR_ABORTED"
    },
    {
      "url": "http://127.0.0.1:64092/_nuxt/@fs/D:/DEVJUANMARCOS/PROJETOS/KEENER/VIA%20REVERSA/V2/ViaReversaV2_Front/node_modules/reka-ui/dist/HoverCard/HoverCardTrigger.js?v=c692b6b6",
      "method": "GET",
      "failure": "net::ERR_ABORTED"
    },
    {
      "url": "http://127.0.0.1:64092/_nuxt/@fs/D:/DEVJUANMARCOS/PROJETOS/KEENER/VIA%20REVERSA/V2/ViaReversaV2_Front/node_modules/reka-ui/dist/Select/BubbleSelect.js?v=c692b6b6",
      "method": "GET",
      "failure": "net::ERR_ABORTED"
    },
    {
      "url": "http://127.0.0.1:64092/_nuxt/@fs/D:/DEVJUANMARCOS/PROJETOS/KEENER/VIA%20REVERSA/V2/ViaReversaV2_Front/node_modules/reka-ui/dist/Toast/ToastRoot.js?v=c692b6b6",
      "method": "GET",
      "failure": "net::ERR_ABORTED"
    },
    {
      "url": "http://127.0.0.1:64092/_nuxt/@fs/D:/DEVJUANMARCOS/PROJETOS/KEENER/VIA%20REVERSA/V2/ViaReversaV2_Front/node_modules/reka-ui/dist/RadioGroup/utils.js?v=c692b6b6",
      "method": "GET",
      "failure": "net::ERR_ABORTED"
    },
    {
      "url": "http://127.0.0.1:64092/_nuxt/@fs/D:/DEVJUANMARCOS/PROJETOS/KEENER/VIA%20REVERSA/V2/ViaReversaV2_Front/node_modules/reka-ui/dist/NavigationMenu/NavigationMenuContent.js?v=c692b6b6",
      "method": "GET",
      "failure": "net::ERR_ABORTED"
    },
    {
      "url": "http://127.0.0.1:64092/_nuxt/@fs/D:/DEVJUANMARCOS/PROJETOS/KEENER/VIA%20REVERSA/V2/ViaReversaV2_Front/node_modules/reka-ui/dist/YearRangePicker/YearRangePickerGridBody.js?v=c692b6b6",
      "method": "GET",
      "failure": "net::ERR_ABORTED"
    },
    {
      "url": "http://127.0.0.1:64092/_nuxt/@fs/D:/DEVJUANMARCOS/PROJETOS/KEENER/VIA%20REVERSA/V2/ViaReversaV2_Front/node_modules/reka-ui/dist/MonthPicker/MonthPickerGridBody.js?v=c692b6b6",
      "method": "GET",
      "failure": "net::ERR_ABORTED"
    },
    {
      "url": "http://127.0.0.1:64092/_nuxt/@fs/D:/DEVJUANMARCOS/PROJETOS/KEENER/VIA%20REVERSA/V2/ViaReversaV2_Front/node_modules/reka-ui/dist/Menubar/MenubarRoot.js?v=c692b6b6",
      "method": "GET",
      "failure": "net::ERR_ABORTED"
    },
    {
      "url": "http://127.0.0.1:64092/_nuxt/@fs/D:/DEVJUANMARCOS/PROJETOS/KEENER/VIA%20REVERSA/V2/ViaReversaV2_Front/node_modules/reka-ui/dist/MonthPicker/MonthPickerRoot.js?v=c692b6b6",
      "method": "GET",
      "failure": "net::ERR_ABORTED"
    },
    {
      "url": "http://127.0.0.1:64092/_nuxt/@fs/D:/DEVJUANMARCOS/PROJETOS/KEENER/VIA%20REVERSA/V2/ViaReversaV2_Front/node_modules/reka-ui/dist/HoverCard/utils.js?v=c692b6b6",
      "method": "GET",
      "failure": "net::ERR_ABORTED"
    },
    {
      "url": "http://127.0.0.1:64092/_nuxt/@fs/D:/DEVJUANMARCOS/PROJETOS/KEENER/VIA%20REVERSA/V2/ViaReversaV2_Front/node_modules/reka-ui/dist/Rating/RatingItem.js?v=c692b6b6",
      "method": "GET",
      "failure": "net::ERR_ABORTED"
    },
    {
      "url": "http://127.0.0.1:64092/_nuxt/@fs/D:/DEVJUANMARCOS/PROJETOS/KEENER/VIA%20REVERSA/V2/ViaReversaV2_Front/node_modules/reka-ui/dist/YearRangePicker/YearRangePickerGrid.js?v=c692b6b6",
      "method": "GET",
      "failure": "net::ERR_ABORTED"
    },
    {
      "url": "http://127.0.0.1:64092/_nuxt/@fs/D:/DEVJUANMARCOS/PROJETOS/KEENER/VIA%20REVERSA/V2/ViaReversaV2_Front/node_modules/@nuxt/ui/dist/runtime/utils/locale.js?v=c692b6b6",
      "method": "GET",
      "failure": "net::ERR_ABORTED"
    },
    {
      "url": "http://127.0.0.1:64092/_nuxt/@fs/D:/DEVJUANMARCOS/PROJETOS/KEENER/VIA%20REVERSA/V2/ViaReversaV2_Front/node_modules/reka-ui/dist/Popover/PopoverContent.js?v=c692b6b6",
      "method": "GET",
      "failure": "net::ERR_ABORTED"
    },
    {
      "url": "http://127.0.0.1:64092/_nuxt/@id/virtual:nuxt:D%3A%2FDEVJUANMARCOS%2FPROJETOS%2FKEENER%2FVIA%20REVERSA%2FV2%2FViaReversaV2_Front%2F.nuxt%2Fui%2Ftoaster.ts",
      "method": "GET",
      "failure": "net::ERR_ABORTED"
    },
    {
      "url": "http://127.0.0.1:64092/_nuxt/@fs/D:/DEVJUANMARCOS/PROJETOS/KEENER/VIA%20REVERSA/V2/ViaReversaV2_Front/node_modules/reka-ui/dist/Pagination/PaginationEllipsis.js?v=c692b6b6",
      "method": "GET",
      "failure": "net::ERR_ABORTED"
    },
    {
      "url": "http://127.0.0.1:64092/_nuxt/@fs/D:/DEVJUANMARCOS/PROJETOS/KEENER/VIA%20REVERSA/V2/ViaReversaV2_Front/node_modules/reka-ui/dist/RangeCalendar/RangeCalendarNext.js?v=c692b6b6",
      "method": "GET",
      "failure": "net::ERR_ABORTED"
    },
    {
      "url": "http://127.0.0.1:64092/_nuxt/@fs/D:/DEVJUANMARCOS/PROJETOS/KEENER/VIA%20REVERSA/V2/ViaReversaV2_Front/node_modules/reka-ui/dist/utils/callPanelCallbacks.js?v=c692b6b6",
      "method": "GET",
      "failure": "net::ERR_ABORTED"
    },
    {
      "url": "http://127.0.0.1:64092/_nuxt/@fs/D:/DEVJUANMARCOS/PROJETOS/KEENER/VIA%20REVERSA/V2/ViaReversaV2_Front/node_modules/reka-ui/dist/YearPicker/YearPickerGrid.js?v=c692b6b6",
      "method": "GET",
      "failure": "net::ERR_ABORTED"
    },
    {
      "url": "http://127.0.0.1:64092/_nuxt/@fs/D:/DEVJUANMARCOS/PROJETOS/KEENER/VIA%20REVERSA/V2/ViaReversaV2_Front/node_modules/reka-ui/dist/NavigationMenu/NavigationMenuViewport.js?v=c692b6b6",
      "method": "GET",
      "failure": "net::ERR_ABORTED"
    },
    {
      "url": "http://127.0.0.1:64092/_nuxt/@fs/D:/DEVJUANMARCOS/PROJETOS/KEENER/VIA%20REVERSA/V2/ViaReversaV2_Front/node_modules/reka-ui/dist/Popover/PopoverAnchor.js?v=c692b6b6",
      "method": "GET",
      "failure": "net::ERR_ABORTED"
    },
    {
      "url": "http://127.0.0.1:64092/_nuxt/@fs/D:/DEVJUANMARCOS/PROJETOS/KEENER/VIA%20REVERSA/V2/ViaReversaV2_Front/node_modules/reka-ui/dist/utils/dom.js?v=c692b6b6",
      "method": "GET",
      "failure": "net::ERR_ABORTED"
    },
    {
      "url": "http://127.0.0.1:64092/_nuxt/@fs/D:/DEVJUANMARCOS/PROJETOS/KEENER/VIA%20REVERSA/V2/ViaReversaV2_Front/node_modules/reka-ui/dist/MonthPicker/MonthPickerCell.js?v=c692b6b6",
      "method": "GET",
      "failure": "net::ERR_ABORTED"
    },
    {
      "url": "http://127.0.0.1:64092/_nuxt/@fs/D:/DEVJUANMARCOS/PROJETOS/KEENER/VIA%20REVERSA/V2/ViaReversaV2_Front/node_modules/reka-ui/dist/RadioGroup/RadioGroupIndicator.js?v=c692b6b6",
      "method": "GET",
      "failure": "net::ERR_ABORTED"
    },
    {
      "url": "http://127.0.0.1:64092/_nuxt/@fs/D:/DEVJUANMARCOS/PROJETOS/KEENER/VIA%20REVERSA/V2/ViaReversaV2_Front/node_modules/reka-ui/dist/Select/SelectValue.js?v=c692b6b6",
      "method": "GET",
      "failure": "net::ERR_ABORTED"
    },
    {
      "url": "http://127.0.0.1:64092/_nuxt/@fs/D:/DEVJUANMARCOS/PROJETOS/KEENER/VIA%20REVERSA/V2/ViaReversaV2_Front/node_modules/reka-ui/dist/Select/SelectContent.js?v=c692b6b6",
      "method": "GET",
      "failure": "net::ERR_ABORTED"
    },
    {
      "url": "http://127.0.0.1:64092/_nuxt/@fs/D:/DEVJUANMARCOS/PROJETOS/KEENER/VIA%20REVERSA/V2/ViaReversaV2_Front/node_modules/@tanstack/vue-virtual/dist/esm/index.js?v=c692b6b6",
      "method": "GET",
      "failure": "net::ERR_ABORTED"
    },
    {
      "url": "http://127.0.0.1:64092/_nuxt/@fs/D:/DEVJUANMARCOS/PROJETOS/KEENER/VIA%20REVERSA/V2/ViaReversaV2_Front/node_modules/reka-ui/dist/Rating/RatingItemIndicator.js?v=c692b6b6",
      "method": "GET",
      "failure": "net::ERR_ABORTED"
    },
    {
      "url": "http://127.0.0.1:64092/_nuxt/@fs/D:/DEVJUANMARCOS/PROJETOS/KEENER/VIA%20REVERSA/V2/ViaReversaV2_Front/node_modules/reka-ui/dist/Toolbar/ToolbarToggleGroup.js?v=c692b6b6",
      "method": "GET",
      "failure": "net::ERR_ABORTED"
    },
    {
      "url": "http://127.0.0.1:64092/_nuxt/@fs/D:/DEVJUANMARCOS/PROJETOS/KEENER/VIA%20REVERSA/V2/ViaReversaV2_Front/node_modules/reka-ui/dist/Progress/ProgressIndicator.js?v=c692b6b6",
      "method": "GET",
      "failure": "net::ERR_ABORTED"
    },
    {
      "url": "http://127.0.0.1:64092/_nuxt/@fs/D:/DEVJUANMARCOS/PROJETOS/KEENER/VIA%20REVERSA/V2/ViaReversaV2_Front/node_modules/reka-ui/dist/RangeCalendar/RangeCalendarHeading.js?v=c692b6b6",
      "method": "GET",
      "failure": "net::ERR_ABORTED"
    },
    {
      "url": "http://127.0.0.1:64092/_nuxt/@fs/D:/DEVJUANMARCOS/PROJETOS/KEENER/VIA%20REVERSA/V2/ViaReversaV2_Front/node_modules/reka-ui/dist/RangeCalendar/RangeCalendarHeader.js?v=c692b6b6",
      "method": "GET",
      "failure": "net::ERR_ABORTED"
    },
    {
      "url": "http://127.0.0.1:64092/_nuxt/@fs/D:/DEVJUANMARCOS/PROJETOS/KEENER/VIA%20REVERSA/V2/ViaReversaV2_Front/node_modules/reka-ui/dist/Menubar/MenubarGroup.js?v=c692b6b6",
      "method": "GET",
      "failure": "net::ERR_ABORTED"
    },
    {
      "url": "http://127.0.0.1:64092/_nuxt/@fs/D:/DEVJUANMARCOS/PROJETOS/KEENER/VIA%20REVERSA/V2/ViaReversaV2_Front/node_modules/reka-ui/dist/Tooltip/TooltipPortal.js?v=c692b6b6",
      "method": "GET",
      "failure": "net::ERR_ABORTED"
    },
    {
      "url": "http://127.0.0.1:64092/_nuxt/@fs/D:/DEVJUANMARCOS/PROJETOS/KEENER/VIA%20REVERSA/V2/ViaReversaV2_Front/node_modules/reka-ui/dist/component/BaseSeparator.js?v=c692b6b6",
      "method": "GET",
      "failure": "net::ERR_ABORTED"
    },
    {
      "url": "http://127.0.0.1:64092/_nuxt/@fs/D:/DEVJUANMARCOS/PROJETOS/KEENER/VIA%20REVERSA/V2/ViaReversaV2_Front/node_modules/reka-ui/dist/Rating/RatingRoot.js?v=c692b6b6",
      "method": "GET",
      "failure": "net::ERR_ABORTED"
    },
    {
      "url": "http://127.0.0.1:64092/_nuxt/@fs/D:/DEVJUANMARCOS/PROJETOS/KEENER/VIA%20REVERSA/V2/ViaReversaV2_Front/node_modules/reka-ui/dist/NavigationMenu/utils.js?v=c692b6b6",
      "method": "GET",
      "failure": "net::ERR_ABORTED"
    },
    {
      "url": "http://127.0.0.1:64092/_nuxt/@fs/D:/DEVJUANMARCOS/PROJETOS/KEENER/VIA%20REVERSA/V2/ViaReversaV2_Front/node_modules/reka-ui/dist/Select/SelectProvider.js?v=c692b6b6",
      "method": "GET",
      "failure": "net::ERR_ABORTED"
    },
    {
      "url": "http://127.0.0.1:64092/_nuxt/@fs/D:/DEVJUANMARCOS/PROJETOS/KEENER/VIA%20REVERSA/V2/ViaReversaV2_Front/node_modules/reka-ui/dist/Select/SelectContentImpl.js?v=c692b6b6",
      "method": "GET",
      "failure": "net::ERR_ABORTED"
    },
    {
      "url": "http://127.0.0.1:64092/_nuxt/@fs/D:/DEVJUANMARCOS/PROJETOS/KEENER/VIA%20REVERSA/V2/ViaReversaV2_Front/node_modules/reka-ui/dist/Menubar/MenubarItemIndicator.js?v=c692b6b6",
      "method": "GET",
      "failure": "net::ERR_ABORTED"
    },
    {
      "url": "http://127.0.0.1:64092/_nuxt/@fs/D:/DEVJUANMARCOS/PROJETOS/KEENER/VIA%20REVERSA/V2/ViaReversaV2_Front/node_modules/@nuxt/ui/dist/runtime/composables/useOverlay.js?v=c692b6b6",
      "method": "GET",
      "failure": "net::ERR_ABORTED"
    },
    {
      "url": "http://127.0.0.1:64092/_nuxt/@fs/D:/DEVJUANMARCOS/PROJETOS/KEENER/VIA%20REVERSA/V2/ViaReversaV2_Front/node_modules/reka-ui/dist/NumberField/utils.js?v=c692b6b6",
      "method": "GET",
      "failure": "net::ERR_ABORTED"
    },
    {
      "url": "http://127.0.0.1:64092/_nuxt/@fs/D:/DEVJUANMARCOS/PROJETOS/KEENER/VIA%20REVERSA/V2/ViaReversaV2_Front/node_modules/reka-ui/dist/utils/assert.js?v=c692b6b6",
      "method": "GET",
      "failure": "net::ERR_ABORTED"
    }
  ],
  "consoleLog": [],
  "pageErrors": []
}
